[{"id":906,"imgName":"sprigatito","name":"Felori","shape":"","color":{"l":0.52,"c":0.18,"h":142},"types":["grass"],"genus":"","flavorText":"","formDescription":""},{"id":907,"imgName":"floragato","name":"Feliospa","shape":"","color":{"l":0.52,"c":0.18,"h":142},"types":["grass"],"genus":"","flavorText":"","formDescription":""},{"id":908,"imgName":"meowscarada","name":"Maskagato","shape":"","color":{"l":0.52,"c":0.18,"h":142},"types":["grass","dark"],"genus":"Magier","flavorText":"","formDescription":""},{"id":909,"imgName":"fuecoco","name":"Krokel","shape":"","color":{"l":0.63,"c":0.26,"h":29},"types":["fire"],"genus":"Feuerkroko","flavorText":"","formDescription":""},{"id":910,"imgName":"crocalor","name":"Lokroko","shape":"","color":{"l":0.63,"c":0.26,"h":29},"types":["fire"],"genus":"Feuerkroko","flavorText":"","formDescription":""},{"id":911,"imgName":"skeledirge","name":"Skelokrok","shape":"","color":{"l":0.63,"c":0.26,"h":29},"types":["fire","ghost"],"genus":"Sänger","flavorText":"","formDescription":""},{"id":912,"imgName":"quaxly","name":"Kwaks","shape":"","color":{"l":1,"c":0,"h":0},"types":["water"],"genus":"Jungente","flavorText":"","formDescription":""},{"id":913,"imgName":"quaxwell","name":"Fuentente","shape":"","color":{"l":0.45,"c":0.31,"h":264},"types":["water"],"genus":"Übung","flavorText":"","formDescription":""},{"id":914,"imgName":"quaquaval","name":"Bailonda","shape":"","color":{"l":0.45,"c":0.31,"h":264},"types":["water","fighting"],"genus":"Tänzer","flavorText":"","formDescription":""},{"id":915,"imgName":"lechonk","name":"Ferkuli","shape":"","color":{"l":0.6,"c":0,"h":0},"types":["normal"],"genus":"Schwein","flavorText":"","formDescription":""},{"id":917,"imgName":"tarountula","name":"Tarundel","shape":"","color":{"l":1,"c":0,"h":0},"types":["bug"],"genus":"Fadenkugel","flavorText":"","formDescription":""},{"id":918,"imgName":"spidops","name":"Spinsidias","shape":"","color":{"l":0.52,"c":0.18,"h":142},"types":["bug"],"genus":"Falle","flavorText":"","formDescription":""},{"id":919,"imgName":"nymble","name":"Micrick","shape":"","color":{"l":0.6,"c":0,"h":0},"types":["bug"],"genus":"Heuschrecke","flavorText":"","formDescription":""},{"id":920,"imgName":"lokix","name":"Lextremo","shape":"","color":{"l":0.6,"c":0,"h":0},"types":["bug","dark"],"genus":"Heuschrecke","flavorText":"","formDescription":""},{"id":921,"imgName":"pawmi","name":"Pamo","shape":"","color":{"l":0.97,"c":0.21,"h":110},"types":["electric"],"genus":"Maus","flavorText":"","formDescription":""},{"id":922,"imgName":"pawmo","name":"Pamamo","shape":"","color":{"l":0.97,"c":0.21,"h":110},"types":["electric","fighting"],"genus":"Maus","flavorText":"","formDescription":""},{"id":923,"imgName":"pawmot","name":"Pamomamo","shape":"","color":{"l":0.97,"c":0.21,"h":110},"types":["electric","fighting"],"genus":"Behandlung","flavorText":"","formDescription":""},{"id":924,"imgName":"tandemaus","name":"Zwieps","shape":"","color":{"l":1,"c":0,"h":0},"types":["normal"],"genus":"Paar","flavorText":"","formDescription":""},{"id":926,"imgName":"fidough","name":"Hefel","shape":"","color":{"l":0.97,"c":0.21,"h":110},"types":["fairy"],"genus":"Welpe","flavorText":"","formDescription":""},{"id":927,"imgName":"dachsbun","name":"Backel","shape":"","color":{"l":0.48,"c":0.16,"h":26},"types":["fairy"],"genus":"Hund","flavorText":"","formDescription":""},{"id":928,"imgName":"smoliv","name":"Olini","shape":"","color":{"l":0.52,"c":0.18,"h":142},"types":["grass","normal"],"genus":"Olive","flavorText":"","formDescription":""},{"id":929,"imgName":"dolliv","name":"Olivinio","shape":"","color":{"l":0.52,"c":0.18,"h":142},"types":["grass","normal"],"genus":"Olive","flavorText":"","formDescription":""},{"id":930,"imgName":"arboliva","name":"Olithena","shape":"","color":{"l":0.52,"c":0.18,"h":142},"types":["grass","normal"],"genus":"Olive","flavorText":"","formDescription":""},{"id":932,"imgName":"nacli","name":"Geosali","shape":"","color":{"l":0.48,"c":0.16,"h":26},"types":["rock"],"genus":"Steinsalz","flavorText":"","formDescription":""},{"id":933,"imgName":"naclstack","name":"Sedisal","shape":"","color":{"l":0.48,"c":0.16,"h":26},"types":["rock"],"genus":"Steinsalz","flavorText":"","formDescription":""},{"id":934,"imgName":"garganacl","name":"Saltigant","shape":"","color":{"l":0.48,"c":0.16,"h":26},"types":["rock"],"genus":"Steinsalz","flavorText":"","formDescription":""},{"id":935,"imgName":"charcadet","name":"Knarbon","shape":"","color":{"l":0.63,"c":0.26,"h":29},"types":["fire"],"genus":"Feuerkind","flavorText":"","formDescription":""},{"id":936,"imgName":"armarouge","name":"Crimanzo","shape":"","color":{"l":0.63,"c":0.26,"h":29},"types":["fire","psychic"],"genus":"Feuerrüstung","flavorText":"","formDescription":""},{"id":937,"imgName":"ceruledge","name":"Azugladis","shape":"","color":{"l":0.45,"c":0.31,"h":264},"types":["fire","ghost"],"genus":"Feuerklingen","flavorText":"","formDescription":""},{"id":938,"imgName":"tadbulb","name":"Blipp","shape":"","color":{"l":0.97,"c":0.21,"h":110},"types":["electric"],"genus":"Stromquappe","flavorText":"","formDescription":""},{"id":939,"imgName":"bellibolt","name":"Wampitz","shape":"","color":{"l":0.52,"c":0.18,"h":142},"types":["electric"],"genus":"Stromfrosch","flavorText":"","formDescription":""},{"id":940,"imgName":"wattrel","name":"Voltrel","shape":"","color":{"l":0,"c":0,"h":0},"types":["electric","flying"],"genus":"Sturmvogel","flavorText":"","formDescription":""},{"id":941,"imgName":"kilowattrel","name":"Voltrean","shape":"","color":{"l":0.97,"c":0.21,"h":110},"types":["electric","flying"],"genus":"Fregattvogel","flavorText":"","formDescription":""},{"id":942,"imgName":"maschiff","name":"Mobtiff","shape":"","color":{"l":0.48,"c":0.16,"h":26},"types":["dark"],"genus":"Halbstark","flavorText":"","formDescription":""},{"id":943,"imgName":"mabosstiff","name":"Mastifioso","shape":"","color":{"l":0.6,"c":0,"h":0},"types":["dark"],"genus":"Oberhaupt","flavorText":"","formDescription":""},{"id":944,"imgName":"shroodle","name":"Sproxi","shape":"","color":{"l":0.6,"c":0,"h":0},"types":["poison","normal"],"genus":"Giftmaus","flavorText":"","formDescription":""},{"id":945,"imgName":"grafaiai","name":"Affiti","shape":"","color":{"l":0.6,"c":0,"h":0},"types":["poison","normal"],"genus":"Giftaffe","flavorText":"","formDescription":""},{"id":946,"imgName":"bramblin","name":"Weherba","shape":"","color":{"l":0.48,"c":0.16,"h":26},"types":["grass","ghost"],"genus":"Rollgras","flavorText":"","formDescription":""},{"id":947,"imgName":"brambleghast","name":"Horrerba","shape":"","color":{"l":0.48,"c":0.16,"h":26},"types":["grass","ghost"],"genus":"Rollgras","flavorText":"","formDescription":""},{"id":948,"imgName":"toedscool","name":"Tentagra","shape":"","color":{"l":0.97,"c":0.21,"h":110},"types":["ground","grass"],"genus":"Quallenpilz","flavorText":"","formDescription":""},{"id":949,"imgName":"toedscruel","name":"Tenterra","shape":"","color":{"l":0,"c":0,"h":0},"types":["ground","grass"],"genus":"Quallenpilz","flavorText":"","formDescription":""},{"id":950,"imgName":"klawf","name":"Klibbe","shape":"","color":{"l":0.63,"c":0.26,"h":29},"types":["rock"],"genus":"Lauer","flavorText":"","formDescription":""},{"id":951,"imgName":"capsakid","name":"Chilingel","shape":"","color":{"l":0.52,"c":0.18,"h":142},"types":["grass"],"genus":"Habanero","flavorText":"","formDescription":""},{"id":952,"imgName":"scovillain","name":"Halupenjo","shape":"","color":{"l":0.52,"c":0.18,"h":142},"types":["grass","fire"],"genus":"Habanero","flavorText":"","formDescription":""},{"id":953,"imgName":"rellor","name":"Relluk","shape":"","color":{"l":0.48,"c":0.16,"h":26},"types":["bug"],"genus":"Wälz","flavorText":"","formDescription":""},{"id":954,"imgName":"rabsca","name":"Skarabaks","shape":"","color":{"l":0.52,"c":0.18,"h":142},"types":["bug","psychic"],"genus":"Wälz","flavorText":"","formDescription":""},{"id":955,"imgName":"flittle","name":"Flattutu","shape":"","color":{"l":0.97,"c":0.21,"h":110},"types":["psychic"],"genus":"Rüschen","flavorText":"","formDescription":""},{"id":956,"imgName":"espathra","name":"Psiopatra","shape":"","color":{"l":0.97,"c":0.21,"h":110},"types":["psychic"],"genus":"Strauß","flavorText":"","formDescription":""},{"id":957,"imgName":"tinkatink","name":"Forgita","shape":"","color":{"l":0.87,"c":0.07,"h":7},"types":["fairy","steel"],"genus":"Schmied","flavorText":"","formDescription":""},{"id":958,"imgName":"tinkatuff","name":"Tafforgita","shape":"","color":{"l":0.87,"c":0.07,"h":7},"types":["fairy","steel"],"genus":"Hammer","flavorText":"","formDescription":""},{"id":959,"imgName":"tinkaton","name":"Granforgita","shape":"","color":{"l":0.87,"c":0.07,"h":7},"types":["fairy","steel"],"genus":"Hammer","flavorText":"","formDescription":""},{"id":960,"imgName":"wiglett","name":"Schligda","shape":"","color":{"l":1,"c":0,"h":0},"types":["water"],"genus":"Meeraal","flavorText":"","formDescription":""},{"id":961,"imgName":"wugtrio","name":"Schligdri","shape":"","color":{"l":0.63,"c":0.26,"h":29},"types":["water"],"genus":"Meeraal","flavorText":"","formDescription":""},{"id":962,"imgName":"bombirdier","name":"Adebom","shape":"","color":{"l":1,"c":0,"h":0},"types":["flying","dark"],"genus":"Abwurf","flavorText":"","formDescription":""},{"id":963,"imgName":"finizen","name":"Normifin","shape":"","color":{"l":0.45,"c":0.31,"h":264},"types":["water"],"genus":"Delfin","flavorText":"","formDescription":""},{"id":965,"imgName":"varoom","name":"Knattox","shape":"","color":{"l":0.6,"c":0,"h":0},"types":["steel","poison"],"genus":"Einzylinder","flavorText":"","formDescription":""},{"id":966,"imgName":"revavroom","name":"Knattatox","shape":"","color":{"l":0.6,"c":0,"h":0},"types":["steel","poison"],"genus":"Mehrzylinder","flavorText":"","formDescription":""},{"id":967,"imgName":"cyclizar","name":"Mopex","shape":"","color":{"l":0.52,"c":0.18,"h":142},"types":["dragon","normal"],"genus":"Ritt","flavorText":"","formDescription":""},{"id":968,"imgName":"orthworm","name":"Schlurm","shape":"","color":{"l":0.87,"c":0.07,"h":7},"types":["steel"],"genus":"Regenwurm","flavorText":"","formDescription":""},{"id":969,"imgName":"glimmet","name":"Lumispross","shape":"","color":{"l":0.45,"c":0.31,"h":264},"types":["rock","poison"],"genus":"Erz","flavorText":"","formDescription":""},{"id":970,"imgName":"glimmora","name":"Lumiflora","shape":"","color":{"l":0.45,"c":0.31,"h":264},"types":["rock","poison"],"genus":"Erz","flavorText":"","formDescription":""},{"id":971,"imgName":"greavard","name":"Gruff","shape":"","color":{"l":1,"c":0,"h":0},"types":["ghost"],"genus":"Geisterhund","flavorText":"","formDescription":""},{"id":972,"imgName":"houndstone","name":"Friedwuff","shape":"","color":{"l":1,"c":0,"h":0},"types":["ghost"],"genus":"Geisterhund","flavorText":"","formDescription":""},{"id":973,"imgName":"flamigo","name":"Flaminkno","shape":"","color":{"l":0.87,"c":0.07,"h":7},"types":["flying","fighting"],"genus":"Synchron","flavorText":"","formDescription":""},{"id":974,"imgName":"cetoddle","name":"Flaniwal","shape":"","color":{"l":1,"c":0,"h":0},"types":["ice"],"genus":"Landwal","flavorText":"","formDescription":""},{"id":975,"imgName":"cetitan","name":"Kolowal","shape":"","color":{"l":1,"c":0,"h":0},"types":["ice"],"genus":"Landwal","flavorText":"","formDescription":""},{"id":976,"imgName":"veluza","name":"Agiluza","shape":"","color":{"l":0.6,"c":0,"h":0},"types":["water","psychic"],"genus":"Abtrennung","flavorText":"","formDescription":""},{"id":977,"imgName":"dondozo","name":"Heerashai","shape":"","color":{"l":0.45,"c":0.31,"h":264},"types":["water"],"genus":"Großwels","flavorText":"","formDescription":""},{"id":979,"imgName":"annihilape","name":"Epitaff","shape":"","color":{"l":0.6,"c":0,"h":0},"types":["fighting","ghost"],"genus":"Zornaffe","flavorText":"","formDescription":""},{"id":980,"imgName":"clodsire","name":"Suelord","shape":"","color":{"l":0.48,"c":0.16,"h":26},"types":["poison","ground"],"genus":"Dornfisch","flavorText":"","formDescription":""},{"id":981,"imgName":"farigiraf","name":"Farigiraf","shape":"","color":{"l":0.48,"c":0.16,"h":26},"types":["normal","psychic"],"genus":"Langhals","flavorText":"","formDescription":""},{"id":983,"imgName":"kingambit","name":"Gladimperio","shape":"","color":{"l":0,"c":0,"h":0},"types":["dark","steel"],"genus":"Langschwert","flavorText":"","formDescription":""},{"id":984,"imgName":"great-tusk","name":"Riesenzahn","shape":"","color":{"l":0.42,"c":0.19,"h":328},"types":["ground","fighting"],"genus":"Paradox","flavorText":"","formDescription":""},{"id":985,"imgName":"scream-tail","name":"Brüllschweif","shape":"","color":{"l":0.87,"c":0.07,"h":7},"types":["fairy","psychic"],"genus":"Paradox","flavorText":"","formDescription":""},{"id":986,"imgName":"brute-bonnet","name":"Wutpilz","shape":"","color":{"l":0.6,"c":0,"h":0},"types":["grass","dark"],"genus":"Paradox","flavorText":"","formDescription":""},{"id":987,"imgName":"flutter-mane","name":"Flatterhaar","shape":"","color":{"l":0.6,"c":0,"h":0},"types":["ghost","fairy"],"genus":"Paradox","flavorText":"","formDescription":""},{"id":988,"imgName":"slither-wing","name":"Kriechflügel","shape":"","color":{"l":0.63,"c":0.26,"h":29},"types":["bug","fighting"],"genus":"Paradox","flavorText":"","formDescription":""},{"id":989,"imgName":"sandy-shocks","name":"Sandfell","shape":"","color":{"l":0.6,"c":0,"h":0},"types":["electric","ground"],"genus":"Paradox","flavorText":"","formDescription":""},{"id":990,"imgName":"iron-treads","name":"Eisenrad","shape":"","color":{"l":0.6,"c":0,"h":0},"types":["ground","steel"],"genus":"Paradox","flavorText":"","formDescription":""},{"id":991,"imgName":"iron-bundle","name":"Eisenbündel","shape":"","color":{"l":0.63,"c":0.26,"h":29},"types":["ice","water"],"genus":"Paradox","flavorText":"","formDescription":""},{"id":992,"imgName":"iron-hands","name":"Eisenhand","shape":"","color":{"l":0.6,"c":0,"h":0},"types":["fighting","electric"],"genus":"Paradox","flavorText":"","formDescription":""},{"id":993,"imgName":"iron-jugulis","name":"Eisenhals","shape":"","color":{"l":0.45,"c":0.31,"h":264},"types":["dark","flying"],"genus":"Paradox","flavorText":"","formDescription":""},{"id":994,"imgName":"iron-moth","name":"Eisenfalter","shape":"","color":{"l":0.97,"c":0.21,"h":110},"types":["fire","poison"],"genus":"Paradox","flavorText":"","formDescription":""},{"id":995,"imgName":"iron-thorns","name":"Eisendorn","shape":"","color":{"l":0.52,"c":0.18,"h":142},"types":["rock","electric"],"genus":"Paradox","flavorText":"","formDescription":""},{"id":996,"imgName":"frigibax","name":"Frospino","shape":"","color":{"l":0.6,"c":0,"h":0},"types":["dragon","ice"],"genus":"Eisfinne","flavorText":"","formDescription":""},{"id":997,"imgName":"arctibax","name":"Cryospino","shape":"","color":{"l":0.6,"c":0,"h":0},"types":["dragon","ice"],"genus":"Eisfinne","flavorText":"","formDescription":""},{"id":998,"imgName":"baxcalibur","name":"Espinodon","shape":"","color":{"l":0.6,"c":0,"h":0},"types":["dragon","ice"],"genus":"Eisdrache","flavorText":"","formDescription":""},{"id":999,"imgName":"gimmighoul","name":"Gierspenst","shape":"","color":{"l":0.48,"c":0.16,"h":26},"types":["ghost"],"genus":"Schatztruhe","flavorText":"","formDescription":""},{"id":1000,"imgName":"gholdengo","name":"Monetigo","shape":"","color":{"l":0.97,"c":0.21,"h":110},"types":["steel","ghost"],"genus":"Schatzwesen","flavorText":"","formDescription":""},{"id":1001,"imgName":"wo-chien","name":"Chongjian","shape":"","color":{"l":0.48,"c":0.16,"h":26},"types":["dark","grass"],"genus":"Unheil","flavorText":"","formDescription":""},{"id":1002,"imgName":"chien-pao","name":"Baojian","shape":"","color":{"l":1,"c":0,"h":0},"types":["dark","ice"],"genus":"Unheil","flavorText":"","formDescription":""},{"id":1003,"imgName":"ting-lu","name":"Dinglu","shape":"","color":{"l":0.48,"c":0.16,"h":26},"types":["dark","ground"],"genus":"Unheil","flavorText":"","formDescription":""},{"id":1004,"imgName":"chi-yu","name":"Yuyu","shape":"","color":{"l":0.63,"c":0.26,"h":29},"types":["dark","fire"],"genus":"Unheil","flavorText":"","formDescription":""},{"id":1005,"imgName":"roaring-moon","name":"Donnersichel","shape":"","color":{"l":0.52,"c":0.18,"h":142},"types":["dragon","dark"],"genus":"Paradox","flavorText":"","formDescription":""},{"id":1006,"imgName":"iron-valiant","name":"Eisenkrieger","shape":"","color":{"l":1,"c":0,"h":0},"types":["fairy","fighting"],"genus":"Paradox","flavorText":"","formDescription":""},{"id":1007,"imgName":"koraidon","name":"Koraidon","shape":"","color":{"l":0.63,"c":0.26,"h":29},"types":["fighting","dragon"],"genus":"Paradox","flavorText":"","formDescription":""},{"id":1008,"imgName":"miraidon","name":"Miraidon","shape":"","color":{"l":0.45,"c":0.31,"h":264},"types":["electric","dragon"],"genus":"Paradox","flavorText":"","formDescription":""},{"id":1009,"imgName":"walking-wake","name":"Windewoge","shape":"","color":{"l":0.45,"c":0.31,"h":264},"types":["water","dragon"],"genus":"Paradox","flavorText":"","formDescription":""},{"id":1010,"imgName":"iron-leaves","name":"Eisenblatt","shape":"","color":{"l":0.52,"c":0.18,"h":142},"types":["grass","psychic"],"genus":"Paradox","flavorText":"","formDescription":""},{"id":1011,"imgName":"dipplin","name":"Sirapfel","shape":"","color":{"l":0.52,"c":0.18,"h":142},"types":["grass","dragon"],"genus":"","flavorText":"","formDescription":""},{"id":1012,"imgName":"poltchageist","name":"Mortcha","shape":"","color":{"l":0.52,"c":0.18,"h":142},"types":["grass","ghost"],"genus":"","flavorText":"","formDescription":""},{"id":1013,"imgName":"sinistcha","name":"Fatalitcha","shape":"","color":{"l":0.52,"c":0.18,"h":142},"types":["grass","ghost"],"genus":"","flavorText":"","formDescription":""},{"id":1014,"imgName":"okidogi","name":"Boninu","shape":"","color":{"l":0,"c":0,"h":0},"types":["poison","fighting"],"genus":"","flavorText":"","formDescription":""},{"id":1015,"imgName":"munkidori","name":"Benesaru","shape":"","color":{"l":0,"c":0,"h":0},"types":["poison","psychic"],"genus":"","flavorText":"","formDescription":""},{"id":1016,"imgName":"fezandipiti","name":"Beatori","shape":"","color":{"l":0,"c":0,"h":0},"types":["poison","fairy"],"genus":"","flavorText":"","formDescription":""},{"id":1017,"imgName":"ogerpon","name":"Ogerpon","shape":"","color":{"l":0.52,"c":0.18,"h":142},"types":["grass"],"genus":"","flavorText":"","formDescription":""},{"id":1018,"imgName":"archaludon","name":"Briduradon","shape":"","color":{"l":1,"c":0,"h":0},"types":["steel","dragon"],"genus":"","flavorText":"","formDescription":""},{"id":1019,"imgName":"hydrapple","name":"Hydrapfel","shape":"","color":{"l":0.52,"c":0.18,"h":142},"types":["grass","dragon"],"genus":"","flavorText":"","formDescription":""},{"id":1020,"imgName":"gouging-fire","name":"Keilflamme","shape":"","color":{"l":0.48,"c":0.16,"h":26},"types":["fire","dragon"],"genus":"","flavorText":"","formDescription":""},{"id":1021,"imgName":"raging-bolt","name":"Furienblitz","shape":"","color":{"l":0.97,"c":0.21,"h":110},"types":["electric","dragon"],"genus":"","flavorText":"","formDescription":""},{"id":1022,"imgName":"iron-boulder","name":"Eisenfels","shape":"","color":{"l":0.6,"c":0,"h":0},"types":["rock","psychic"],"genus":"","flavorText":"","formDescription":""},{"id":1023,"imgName":"iron-crown","name":"Eisenhaupt","shape":"","color":{"l":0.45,"c":0.31,"h":264},"types":["steel","psychic"],"genus":"","flavorText":"","formDescription":""},{"id":1024,"imgName":"terapagos","name":"Terapagos","shape":"","color":{"l":0.45,"c":0.31,"h":264},"types":["normal"],"genus":"","flavorText":"","formDescription":""},{"id":1025,"imgName":"pecharunt","name":"Infamomo","shape":"","color":{"l":0.42,"c":0.19,"h":328},"types":["poison","ghost"],"genus":"","flavorText":"","formDescription":""}]