{"id":503,"imgName":"samurott","name":"Samurott","shape":"","color":{"l":0.45,"c":0.31,"h":264},"types":["water"],"genus":"Pokémon Majestuoso","flavorText":"En un abrir y cerrar de ojos, puede desenvainar y\nenvainar los sables que hay en sus patas delanteras.","formDescription":"","previous":{"id":502,"imgName":"dewott","name":"Dewott","shape":"","color":{"l":0.45,"c":0.31,"h":264},"types":["water"],"genus":"Pokémon Superación","flavorText":"Gran espadachín. Utiliza sus dos vieiras con soltura al\nejecutar las técnicas que aprende con una disciplina\nespartana.","formDescription":""},"next":{"id":504,"imgName":"patrat","name":"Patrat","shape":"","color":{"l":0.48,"c":0.16,"h":26},"types":["normal"],"genus":"Pokémon Explorador","flavorText":"Almacena víveres en unas bolsas en sus mofletes y\nvigila durante días. Hace señales con la cola a sus\ncompañeros.","formDescription":""},"evolution":{"pokemon":{"id":501,"imgName":"oshawott","name":"Oshawott","shape":"","color":{"l":0.45,"c":0.31,"h":264},"types":["water"],"genus":"Pokémon Nutria","flavorText":"La vieira de su ombligo no solo sirve como arma, sino\ntambién como instrumento para cortar las bayas que\nestén duras.","formDescription":""},"details":[],"next":[{"pokemon":{"id":502,"imgName":"dewott","name":"Dewott","shape":"","color":{"l":0.45,"c":0.31,"h":264},"types":["water"],"genus":"Pokémon Superación","flavorText":"Gran espadachín. Utiliza sus dos vieiras con soltura al\nejecutar las técnicas que aprende con una disciplina\nespartana.","formDescription":""},"details":["level-up"],"next":[{"pokemon":{"id":503,"imgName":"samurott","name":"Samurott","shape":"","color":{"l":0.45,"c":0.31,"h":264},"types":["water"],"genus":"Pokémon Majestuoso","flavorText":"En un abrir y cerrar de ojos, puede desenvainar y\nenvainar los sables que hay en sus patas delanteras.","formDescription":""},"details":["level-up"],"next":[]}]}]},"stats":{"hp":{"value":95,"effort":0},"attack":{"value":100,"effort":0},"defense":{"value":85,"effort":0},"special-attack":{"value":108,"effort":3},"special-defense":{"value":70,"effort":0},"speed":{"value":70,"effort":0}}}