{"id":639,"imgName":"terrakion","name":"Terrakion","shape":"","color":{"l":0.6,"c":0,"h":0},"types":["rock","fighting"],"genus":"Pokémon Gruta","flavorText":"Su potencia al embestir es capaz de derribar las\nmurallas de un castillo. Las leyendas hablan de sus\nproezas.","formDescription":"","previous":{"id":638,"imgName":"cobalion","name":"Cobalion","shape":"","color":{"l":0.45,"c":0.31,"h":264},"types":["steel","fighting"],"genus":"Pokémon Tesón Acero","flavorText":"Posee un cuerpo y un corazón de acero. Basta una\nmirada suya para que Pokémon violentos le\nobedezcan.","formDescription":""},"next":{"id":640,"imgName":"virizion","name":"Virizion","shape":"","color":{"l":0.52,"c":0.18,"h":142},"types":["grass","fighting"],"genus":"Pokémon Prado","flavorText":"Sus cuernos son hojas afiladas. Sacude a sus\nenemigos con sus relampagueantes movimientos y\nlos reduce.","formDescription":""},"evolution":[[{"pokemon":{"id":639,"imgName":"terrakion","name":"Terrakion","shape":"","color":{"l":0.6,"c":0,"h":0},"types":["rock","fighting"],"genus":"Pokémon Gruta","flavorText":"Su potencia al embestir es capaz de derribar las\nmurallas de un castillo. Las leyendas hablan de sus\nproezas.","formDescription":""},"details":[]}]],"stats":{"hp":{"value":91,"effort":0},"attack":{"value":129,"effort":3},"defense":{"value":90,"effort":0},"special-attack":{"value":72,"effort":0},"special-defense":{"value":90,"effort":0},"speed":{"value":108,"effort":0}}}