{"id":374,"imgName":"beldum","name":"Tanhel","shape":"","color":{"l":0.45,"c":0.31,"h":264},"types":["steel","psychic"],"genus":"Eisenkugel-Pokémon","generation":"generation-iii","flavorText":"Es fliegt, indem es eine magnetische Kraft erzeugt,\ndurch die es der natürlichen Anziehungskraft der\nErde trotzt.","formDescription":"","previous":{"id":373,"imgName":"salamence","name":"Brutalanda","shape":"","color":{"l":0.45,"c":0.31,"h":264},"types":["dragon","flying"],"genus":"Drachen-Pokémon","generation":"generation-iii","flavorText":"Wenn es wütend ist, gerät es außer Kontrolle.\nEs zerstört alles mit seinen Klauen und mit Feuer.","formDescription":""},"next":{"id":375,"imgName":"metang","name":"Metang","shape":"","color":{"l":0.45,"c":0.31,"h":264},"types":["steel","psychic"],"genus":"Eisenklauen-Pokémon","generation":"generation-iii","flavorText":"Das Pokémon besteht aus zwei Tanhel. Es bekommt\nselbst dann keinen Kratzer, wenn ein Jet es streift.","formDescription":""},"evolution":[[{"pokemon":{"id":374,"imgName":"beldum","name":"Tanhel","shape":"","color":{"l":0.45,"c":0.31,"h":264},"types":["steel","psychic"],"genus":"Eisenkugel-Pokémon","generation":"generation-iii","flavorText":"Es fliegt, indem es eine magnetische Kraft erzeugt,\ndurch die es der natürlichen Anziehungskraft der\nErde trotzt.","formDescription":""},"details":[]}],[{"pokemon":{"id":375,"imgName":"metang","name":"Metang","shape":"","color":{"l":0.45,"c":0.31,"h":264},"types":["steel","psychic"],"genus":"Eisenklauen-Pokémon","generation":"generation-iii","flavorText":"Das Pokémon besteht aus zwei Tanhel. Es bekommt\nselbst dann keinen Kratzer, wenn ein Jet es streift.","formDescription":""},"details":[{"trigger":"level-up","value":20}]}],[{"pokemon":{"id":376,"imgName":"metagross","name":"Metagross","shape":"","color":{"l":0.45,"c":0.31,"h":264},"types":["steel","psychic"],"genus":"Eisenfuß-Pokémon","generation":"generation-iii","flavorText":"Dank seiner vier vernetzten Hirne kann es Gegner\nbesser als ein Supercomputer mit komplizierten\nFormeln analysieren.","formDescription":""},"details":[{"trigger":"level-up","value":45}]}]],"stats":{"hp":{"value":40,"effort":0},"attack":{"value":55,"effort":0},"defense":{"value":80,"effort":1},"special-attack":{"value":35,"effort":0},"special-defense":{"value":60,"effort":0},"speed":{"value":30,"effort":0}}}