{"id":375,"imgName":"metang","name":"Metang","shape":"Arms","color":{"l":0.45,"c":0.31,"h":264},"types":["steel","psychic"],"genus":"Iron Claw Pokémon","flavorText":"When two BELDUM fuse together, METANG\nis formed. The brains of the BELDUM are\njoined by a magnetic nervous system.\fBy linking its brains magnetically,\nthis POKéMON generates strong\npsychokinetic power.","formDescription":"","stats":{"hp":{"value":60,"effort":0},"attack":{"value":75,"effort":0},"defense":{"value":100,"effort":2},"special-attack":{"value":55,"effort":0},"special-defense":{"value":80,"effort":0},"speed":{"value":50,"effort":0}}}