{"id":485,"imgName":"heatran","name":"Heatran","shape":"Quadrupède","color":{"l":0.48,"c":0.16,"h":26},"types":["fire","steel"],"genus":"Pokémon Caldeira","flavorText":"Son corps est composé d’acier brut\ndont certaines parties ont fondu\nà cause de sa propre chaleur.","formDescription":"","stats":{"hp":{"value":91,"effort":0},"attack":{"value":90,"effort":0},"defense":{"value":106,"effort":0},"special-attack":{"value":130,"effort":3},"special-defense":{"value":106,"effort":0},"speed":{"value":77,"effort":0}}}