{"id":29,"imgName":"nidoran-f","name":"Nidoran♀","shape":"Quadrupède","color":{"l":0.45,"c":0.31,"h":264},"types":["poison"],"genus":"Pokémon Vénépic","flavorText":"Bien qu’il rechigne à se battre, une\ngoutte du poison sécrété par ses\npiquants peut s’avérer fatale.","formDescription":"","previous":{"id":28,"imgName":"sandslash","name":"Sablaireau","shape":"Droit","color":{"l":0.97,"c":0.21,"h":110},"types":["ground"],"genus":"Pokémon Souris","flavorText":"Il se met en boule pour percuter\nl’ennemi. Ses épines aiguisées\nfont beaucoup de dégâts.","formDescription":""},"next":{"id":30,"imgName":"nidorina","name":"Nidorina","shape":"Quadrupède","color":{"l":0.45,"c":0.31,"h":264},"types":["poison"],"genus":"Pokémon Vénépic","flavorText":"Ce Pokémon dresse ses piquants\nen cas de danger. Ils poussent\nmoins vite que ceux de Nidorino.","formDescription":""},"evolution":{"pokemon":{"id":29,"imgName":"nidoran-f","name":"Nidoran♀","shape":"Quadrupède","color":{"l":0.45,"c":0.31,"h":264},"types":["poison"],"genus":"Pokémon Vénépic","flavorText":"Bien qu’il rechigne à se battre, une\ngoutte du poison sécrété par ses\npiquants peut s’avérer fatale.","formDescription":""},"details":[],"next":[{"pokemon":{"id":30,"imgName":"nidorina","name":"Nidorina","shape":"Quadrupède","color":{"l":0.45,"c":0.31,"h":264},"types":["poison"],"genus":"Pokémon Vénépic","flavorText":"Ce Pokémon dresse ses piquants\nen cas de danger. Ils poussent\nmoins vite que ceux de Nidorino.","formDescription":""},"details":["level-up"],"next":[{"pokemon":{"id":31,"imgName":"nidoqueen","name":"Nidoqueen","shape":"Droit","color":{"l":0.45,"c":0.31,"h":264},"types":["poison","ground"],"genus":"Pokémon Perceur","flavorText":"Son corps est recouvert d’écailles\nsolides. Il donnera sa vie pour\nsecourir les petits de son terrier.","formDescription":""},"details":["use-item"],"next":[]}]}]},"stats":{"hp":{"value":55,"effort":1},"attack":{"value":47,"effort":0},"defense":{"value":52,"effort":0},"special-attack":{"value":40,"effort":0},"special-defense":{"value":40,"effort":0},"speed":{"value":41,"effort":0}}}