{"id":336,"imgName":"seviper","name":"Séviper","shape":"Sinueux","color":{"l":0,"c":0,"h":0},"types":["poison"],"genus":"Pokémon Serpacroc","flavorText":"Le rival historique de Mangriff.\nIl affûte la lame de sa queue \nsur les rochers avant le combat.","formDescription":"","previous":{"id":335,"imgName":"zangoose","name":"Mangriff","shape":"Droit","color":{"l":1,"c":0,"h":0},"types":["normal"],"genus":"Pokémon Chat Furet","flavorText":"C’est le rival de Séviper depuis\ndes générations. Ses griffes\naiguisées sont son meilleur atout.","formDescription":""},"next":{"id":337,"imgName":"lunatone","name":"Séléroc","shape":"Balle","color":{"l":0.97,"c":0.21,"h":110},"types":["rock","psychic"],"genus":"Pokémon Météorite","flavorText":"On suppose qu’il est lié au cycle\nlunaire, car il ne sort que les\nsoirs de pleine lune.","formDescription":""},"evolution":[[{"pokemon":{"id":336,"imgName":"seviper","name":"Séviper","shape":"Sinueux","color":{"l":0,"c":0,"h":0},"types":["poison"],"genus":"Pokémon Serpacroc","flavorText":"Le rival historique de Mangriff.\nIl affûte la lame de sa queue \nsur les rochers avant le combat.","formDescription":""},"details":[]}]],"stats":{"hp":{"value":73,"effort":0},"attack":{"value":100,"effort":1},"defense":{"value":60,"effort":0},"special-attack":{"value":100,"effort":1},"special-defense":{"value":60,"effort":0},"speed":{"value":65,"effort":0}}}