{"id":370,"imgName":"luvdisc","name":"Lovdisc","shape":"Poisson","color":{"l":0.87,"c":0.07,"h":7},"types":["water"],"genus":"Pokémon Rendezvous","flavorText":"Un habitant des mers chaudes. On\ndit que le couple qui tombe sur ce\nPokémon connaîtra l’amour éternel.","formDescription":"","stats":{"hp":{"value":43,"effort":0},"attack":{"value":30,"effort":0},"defense":{"value":55,"effort":0},"special-attack":{"value":40,"effort":0},"special-defense":{"value":65,"effort":0},"speed":{"value":97,"effort":1}}}