{"id":549,"imgName":"lilligant","name":"Fragilady","shape":"Goutte","color":{"l":0.52,"c":0.18,"h":142},"types":["grass"],"genus":"Pokémon Chef-Fleur","flavorText":"Même les Dresseurs confirmés ont\ndu mal à faire éclore sa belle fleur.\nUn Pokémon apprécié des célébrités.","formDescription":"","previous":{"id":548,"imgName":"petilil","name":"Chlorobule","shape":"Goutte","color":{"l":0.52,"c":0.18,"h":142},"types":["grass"],"genus":"Pokémon Racine","flavorText":"Les feuilles sur sa tête sont très\namères, mais elles remettent d’aplomb\nles corps les plus éreintés.","formDescription":""},"evolution":[[{"pokemon":{"id":548,"imgName":"petilil","name":"Chlorobule","shape":"Goutte","color":{"l":0.52,"c":0.18,"h":142},"types":["grass"],"genus":"Pokémon Racine","flavorText":"Les feuilles sur sa tête sont très\namères, mais elles remettent d’aplomb\nles corps les plus éreintés.","formDescription":""},"details":[]}],[{"pokemon":{"id":549,"imgName":"lilligant","name":"Fragilady","shape":"Goutte","color":{"l":0.52,"c":0.18,"h":142},"types":["grass"],"genus":"Pokémon Chef-Fleur","flavorText":"Même les Dresseurs confirmés ont\ndu mal à faire éclore sa belle fleur.\nUn Pokémon apprécié des célébrités.","formDescription":""},"details":["use-item"]}]],"stats":{"hp":{"value":70,"effort":0},"attack":{"value":60,"effort":0},"defense":{"value":75,"effort":0},"special-attack":{"value":110,"effort":2},"special-defense":{"value":75,"effort":0},"speed":{"value":90,"effort":0}}}