{"id":587,"imgName":"emolga","name":"Emolga","shape":"Quadrupède","color":{"l":1,"c":0,"h":0},"types":["electric","flying"],"genus":"Pokémon Pteromys","flavorText":"Il accumule dans ses membranes\nl’électricité qu’il produit dans ses\nbajoues, et la relâche tout en planant.","formDescription":"","previous":{"id":586,"imgName":"sawsbuck","name":"Haydaim","shape":"Quadrupède","color":{"l":0.48,"c":0.16,"h":26},"types":["normal","grass"],"genus":"Pokémon Saison","flavorText":"Il change d’habitat selon les saisons.\nLes gens constatent le passage des\nsaisons en regardant ses ramures.","formDescription":""},"next":{"id":588,"imgName":"karrablast","name":"Carabing","shape":"Humanoïde","color":{"l":0.45,"c":0.31,"h":264},"types":["bug"],"genus":"Pokémon Carabe","flavorText":"Un Pokémon mystérieux qui évolue quand\nil reçoit un stimulus électrique en étant\nproche d’un Escargaume.","formDescription":""},"evolution":[[{"pokemon":{"id":587,"imgName":"emolga","name":"Emolga","shape":"Quadrupède","color":{"l":1,"c":0,"h":0},"types":["electric","flying"],"genus":"Pokémon Pteromys","flavorText":"Il accumule dans ses membranes\nl’électricité qu’il produit dans ses\nbajoues, et la relâche tout en planant.","formDescription":""},"details":[]}]],"stats":{"hp":{"value":55,"effort":0},"attack":{"value":75,"effort":0},"defense":{"value":60,"effort":0},"special-attack":{"value":75,"effort":0},"special-defense":{"value":60,"effort":0},"speed":{"value":103,"effort":2}}}