[{"id":387,"imgName":"turtwig","name":"모부기","shape":"","color":{"l":0.52,"c":0.18,"h":142},"types":["grass"],"genus":"어린잎포켓몬","flavorText":"태양의 빛을 쬐어\n전신으로 광합성을 한다.\n등껍질은 흙이 딱딱해진 것이다.","formDescription":"","stats":{"hp":{"value":55,"effort":0},"attack":{"value":68,"effort":1},"defense":{"value":64,"effort":0},"special-attack":{"value":45,"effort":0},"special-defense":{"value":55,"effort":0},"speed":{"value":31,"effort":0}}},{"id":388,"imgName":"grotle","name":"수풀부기","shape":"","color":{"l":0.52,"c":0.18,"h":142},"types":["grass"],"genus":"나무숲포켓몬","flavorText":"숲 속의 물가에서 산다.\n낮에는 숲 밖으로 나와서\n등껍질의 나무에 빛을 쬔다.","formDescription":"","stats":{"hp":{"value":75,"effort":0},"attack":{"value":89,"effort":1},"defense":{"value":85,"effort":1},"special-attack":{"value":55,"effort":0},"special-defense":{"value":65,"effort":0},"speed":{"value":36,"effort":0}}},{"id":389,"imgName":"torterra","name":"토대부기","shape":"","color":{"l":0.52,"c":0.18,"h":142},"types":["grass","ground"],"genus":"대륙포켓몬","flavorText":"오랜 옛날 사람들은 대지\n밑에 거대한 토대부기가\n있다고 공상했었다.","formDescription":"","stats":{"hp":{"value":95,"effort":0},"attack":{"value":109,"effort":2},"defense":{"value":105,"effort":1},"special-attack":{"value":75,"effort":0},"special-defense":{"value":85,"effort":0},"speed":{"value":56,"effort":0}}},{"id":390,"imgName":"chimchar","name":"불꽃숭이","shape":"","color":{"l":0.48,"c":0.16,"h":26},"types":["fire"],"genus":"꼬마원숭이포켓몬","flavorText":"엉덩이의 불꽃은 배에서\n만들어진 가스가 연료다.\n비에 젖어도 꺼지지 않는다.","formDescription":"","stats":{"hp":{"value":44,"effort":0},"attack":{"value":58,"effort":0},"defense":{"value":44,"effort":0},"special-attack":{"value":58,"effort":0},"special-defense":{"value":44,"effort":0},"speed":{"value":61,"effort":1}}},{"id":391,"imgName":"monferno","name":"파이숭이","shape":"","color":{"l":0.48,"c":0.16,"h":26},"types":["fire","fighting"],"genus":"개구쟁이포켓몬","flavorText":"꼬리의 불꽃 세기를\n잘 컨트롤하여 자신에게\n맞는 거리를 두고 싸운다.","formDescription":"","stats":{"hp":{"value":64,"effort":0},"attack":{"value":78,"effort":0},"defense":{"value":52,"effort":0},"special-attack":{"value":78,"effort":1},"special-defense":{"value":52,"effort":0},"speed":{"value":81,"effort":1}}},{"id":392,"imgName":"infernape","name":"초염몽","shape":"","color":{"l":0.48,"c":0.16,"h":26},"types":["fire","fighting"],"genus":"화염포켓몬","flavorText":"머리에서 타오르는 불꽃처럼\n과격한 성격의 포켓몬이다.\n스피드는 누구에게도 지지 않는다.","formDescription":"","stats":{"hp":{"value":76,"effort":0},"attack":{"value":104,"effort":1},"defense":{"value":71,"effort":0},"special-attack":{"value":104,"effort":1},"special-defense":{"value":71,"effort":0},"speed":{"value":108,"effort":1}}},{"id":393,"imgName":"piplup","name":"팽도리","shape":"","color":{"l":0.45,"c":0.31,"h":264},"types":["water"],"genus":"펭귄포켓몬","flavorText":"신세를 지는 것을 싫어한다.\n트레이너의 지시를 듣지 않아\n친해지기 어렵다.","formDescription":"","stats":{"hp":{"value":53,"effort":0},"attack":{"value":51,"effort":0},"defense":{"value":53,"effort":0},"special-attack":{"value":61,"effort":1},"special-defense":{"value":56,"effort":0},"speed":{"value":40,"effort":0}}},{"id":394,"imgName":"prinplup","name":"팽태자","shape":"","color":{"l":0.45,"c":0.31,"h":264},"types":["water"],"genus":"펭귄포켓몬","flavorText":"무리를 만들지 않고 혼자 생활한다.\n어떤 팽태자라도 자신이 제일\n훌륭하다고 생각하는 듯하다.","formDescription":"","stats":{"hp":{"value":64,"effort":0},"attack":{"value":66,"effort":0},"defense":{"value":68,"effort":0},"special-attack":{"value":81,"effort":2},"special-defense":{"value":76,"effort":0},"speed":{"value":50,"effort":0}}},{"id":395,"imgName":"empoleon","name":"엠페르트","shape":"","color":{"l":0.45,"c":0.31,"h":264},"types":["water","steel"],"genus":"황제포켓몬","flavorText":"제트스키와 맞먹는 속도로\n헤엄친다. 날개 가장자리는\n날카롭게 유빙을 절단한다.","formDescription":"","stats":{"hp":{"value":84,"effort":0},"attack":{"value":86,"effort":0},"defense":{"value":88,"effort":0},"special-attack":{"value":111,"effort":3},"special-defense":{"value":101,"effort":0},"speed":{"value":60,"effort":0}}},{"id":396,"imgName":"starly","name":"찌르꼬","shape":"","color":{"l":0.48,"c":0.16,"h":26},"types":["normal","flying"],"genus":"찌르레기포켓몬","flavorText":"많은 수가 무리를 이루어\n행동한다. 몸은 작지만\n날개 치는 힘은 매우 강하다.","formDescription":"","stats":{"hp":{"value":40,"effort":0},"attack":{"value":55,"effort":0},"defense":{"value":30,"effort":0},"special-attack":{"value":30,"effort":0},"special-defense":{"value":30,"effort":0},"speed":{"value":60,"effort":1}}},{"id":397,"imgName":"staravia","name":"찌르버드","shape":"","color":{"l":0.48,"c":0.16,"h":26},"types":["normal","flying"],"genus":"찌르레기포켓몬","flavorText":"큰 그룹을 만들어\n행동하는 습성이 있다.\n그룹 간의 분쟁이 격하다.","formDescription":"","stats":{"hp":{"value":55,"effort":0},"attack":{"value":75,"effort":0},"defense":{"value":50,"effort":0},"special-attack":{"value":40,"effort":0},"special-defense":{"value":40,"effort":0},"speed":{"value":80,"effort":2}}},{"id":398,"imgName":"staraptor","name":"찌르호크","shape":"","color":{"l":0.48,"c":0.16,"h":26},"types":["normal","flying"],"genus":"맹금포켓몬","flavorText":"날개와 발의 근육이 강해\n작은 포켓몬을 붙잡은 채로\n너끈히 날 수 있다.","formDescription":"","stats":{"hp":{"value":85,"effort":0},"attack":{"value":120,"effort":3},"defense":{"value":70,"effort":0},"special-attack":{"value":50,"effort":0},"special-defense":{"value":60,"effort":0},"speed":{"value":100,"effort":0}}},{"id":399,"imgName":"bidoof","name":"비버니","shape":"","color":{"l":0.48,"c":0.16,"h":26},"types":["normal"],"genus":"둥글쥐포켓몬","flavorText":"어떤 것에도 동요하지 않는\n대담한 신경의 소유자다.\n보기보다는 기민하게 활동한다.","formDescription":"","stats":{"hp":{"value":59,"effort":1},"attack":{"value":45,"effort":0},"defense":{"value":40,"effort":0},"special-attack":{"value":35,"effort":0},"special-defense":{"value":40,"effort":0},"speed":{"value":31,"effort":0}}},{"id":400,"imgName":"bibarel","name":"비버통","shape":"","color":{"l":0.48,"c":0.16,"h":26},"types":["normal","water"],"genus":"비버포켓몬","flavorText":"예리한 앞니로 갉아 얻은\n나뭇가지나 뿌리를 쌓아\n물가에 부지런히 보금자리를 만든다.","formDescription":"","stats":{"hp":{"value":79,"effort":0},"attack":{"value":85,"effort":2},"defense":{"value":60,"effort":0},"special-attack":{"value":55,"effort":0},"special-defense":{"value":60,"effort":0},"speed":{"value":71,"effort":0}}},{"id":401,"imgName":"kricketot","name":"귀뚤뚜기","shape":"","color":{"l":0.63,"c":0.26,"h":29},"types":["bug"],"genus":"귀뚜라미포켓몬","flavorText":"더듬이를 서로 부딪쳐 내는\n소리로 동료와 대화한다. 음색은\n가을밤의 정취를 잘 나타낸다.","formDescription":"","stats":{"hp":{"value":37,"effort":0},"attack":{"value":25,"effort":0},"defense":{"value":41,"effort":1},"special-attack":{"value":25,"effort":0},"special-defense":{"value":41,"effort":0},"speed":{"value":25,"effort":0}}},{"id":402,"imgName":"kricketune","name":"귀뚤톡크","shape":"","color":{"l":0.63,"c":0.26,"h":29},"types":["bug"],"genus":"귀뚜라미포켓몬","flavorText":"울 때는 나이프 같은 팔을\n가슴 앞에서 교차시킨다.\n즉흥으로 멜로디를 만든다.","formDescription":"","stats":{"hp":{"value":77,"effort":0},"attack":{"value":85,"effort":2},"defense":{"value":51,"effort":0},"special-attack":{"value":55,"effort":0},"special-defense":{"value":51,"effort":0},"speed":{"value":65,"effort":0}}},{"id":403,"imgName":"shinx","name":"꼬링크","shape":"","color":{"l":0.45,"c":0.31,"h":264},"types":["electric"],"genus":"섬광포켓몬","flavorText":"몸을 움직일 때마다 근육이 늘어났다\n줄어들었다 하여 전기가 발생한다.\n궁지에 몰리면 몸이 빛난다.","formDescription":"","stats":{"hp":{"value":45,"effort":0},"attack":{"value":65,"effort":1},"defense":{"value":34,"effort":0},"special-attack":{"value":40,"effort":0},"special-defense":{"value":34,"effort":0},"speed":{"value":45,"effort":0}}},{"id":404,"imgName":"luxio","name":"럭시오","shape":"","color":{"l":0.45,"c":0.31,"h":264},"types":["electric"],"genus":"전광포켓몬","flavorText":"발톱에서는 한 방에 적을 기절시킬\n정도로 강한 전류가 흐른다.\n여러 마리가 그룹을 이루어 산다.","formDescription":"","stats":{"hp":{"value":60,"effort":0},"attack":{"value":85,"effort":2},"defense":{"value":49,"effort":0},"special-attack":{"value":60,"effort":0},"special-defense":{"value":49,"effort":0},"speed":{"value":60,"effort":0}}},{"id":405,"imgName":"luxray","name":"렌트라","shape":"","color":{"l":0.45,"c":0.31,"h":264},"types":["electric"],"genus":"안광포켓몬","flavorText":"눈동자가 금색으로 빛날 때\n벽의 저편에 숨어 있는\n먹이를 찾아낼 수 있다.","formDescription":"","stats":{"hp":{"value":80,"effort":0},"attack":{"value":120,"effort":3},"defense":{"value":79,"effort":0},"special-attack":{"value":95,"effort":0},"special-defense":{"value":79,"effort":0},"speed":{"value":70,"effort":0}}},{"id":406,"imgName":"budew","name":"꼬몽울","shape":"","color":{"l":0.52,"c":0.18,"h":142},"types":["grass","poison"],"genus":"꽃봉오리포켓몬","flavorText":"따뜻한 햇볕을 쬐면\n봉오리를 펴서 꽃가루를 날린다.\n깨끗한 물 가까이에 거처가 있다.","formDescription":"","stats":{"hp":{"value":40,"effort":0},"attack":{"value":30,"effort":0},"defense":{"value":35,"effort":0},"special-attack":{"value":50,"effort":1},"special-defense":{"value":70,"effort":0},"speed":{"value":55,"effort":0}}},{"id":407,"imgName":"roserade","name":"로즈레이드","shape":"","color":{"l":0.52,"c":0.18,"h":142},"types":["grass","poison"],"genus":"부케포켓몬","flavorText":"달콤한 향기로 먹이를 유인해\n양팔의 독 채찍을 사용하여\n찌르거나 조여서 꼼짝 못하게 한다.","formDescription":"","stats":{"hp":{"value":60,"effort":0},"attack":{"value":70,"effort":0},"defense":{"value":65,"effort":0},"special-attack":{"value":125,"effort":3},"special-defense":{"value":105,"effort":0},"speed":{"value":90,"effort":0}}},{"id":408,"imgName":"cranidos","name":"두개도스","shape":"","color":{"l":0.45,"c":0.31,"h":264},"types":["rock"],"genus":"박치기포켓몬","flavorText":"철구 같은 화석에서\n부활한 고대 포켓몬이다.\n박치기로 먹이를 꼼짝 못하게 한다.","formDescription":"","stats":{"hp":{"value":67,"effort":0},"attack":{"value":125,"effort":1},"defense":{"value":40,"effort":0},"special-attack":{"value":30,"effort":0},"special-defense":{"value":30,"effort":0},"speed":{"value":58,"effort":0}}},{"id":409,"imgName":"rampardos","name":"램펄드","shape":"","color":{"l":0.45,"c":0.31,"h":264},"types":["rock"],"genus":"박치기포켓몬","flavorText":"어떤 충격에도 견딜 수 있는\n두꺼운 두개골에 눌려\n뇌가 자라지 않았다.","formDescription":"","stats":{"hp":{"value":97,"effort":0},"attack":{"value":165,"effort":2},"defense":{"value":60,"effort":0},"special-attack":{"value":65,"effort":0},"special-defense":{"value":50,"effort":0},"speed":{"value":58,"effort":0}}},{"id":410,"imgName":"shieldon","name":"방패톱스","shape":"","color":{"l":0.6,"c":0,"h":0},"types":["rock","steel"],"genus":"실드포켓몬","flavorText":"큰 나무의 줄기에 비벼서\n단단한 얼굴을 닦는 습성이 있다.\n뒤로부터의 공격에 약하다.","formDescription":"","stats":{"hp":{"value":30,"effort":0},"attack":{"value":42,"effort":0},"defense":{"value":118,"effort":1},"special-attack":{"value":42,"effort":0},"special-defense":{"value":88,"effort":0},"speed":{"value":30,"effort":0}}},{"id":411,"imgName":"bastiodon","name":"바리톱스","shape":"","color":{"l":0.6,"c":0,"h":0},"types":["rock","steel"],"genus":"실드포켓몬","flavorText":"옆에 한 줄로 세우면 어떤\n포켓몬이라도 돌파하지 못한다.\n그렇게 하여 아기를 지켜냈다.","formDescription":"","stats":{"hp":{"value":60,"effort":0},"attack":{"value":52,"effort":0},"defense":{"value":168,"effort":2},"special-attack":{"value":47,"effort":0},"special-defense":{"value":138,"effort":0},"speed":{"value":30,"effort":0}}},{"id":412,"imgName":"burmy","name":"도롱충이","shape":"","color":{"l":0.52,"c":0.18,"h":142},"types":["bug"],"genus":"도롱이벌레포켓몬","flavorText":"차가운 초겨울 바람을 막으려고\n작은 가지나 낙엽을 재료로\n도롱이를 만들어 몸을 감싼다.","formDescription":"","stats":{"hp":{"value":40,"effort":0},"attack":{"value":29,"effort":0},"defense":{"value":45,"effort":0},"special-attack":{"value":29,"effort":0},"special-defense":{"value":45,"effort":1},"speed":{"value":36,"effort":0}}},{"id":413,"imgName":"wormadam-plant","name":"도롱마담","shape":"","color":{"l":0.52,"c":0.18,"h":142},"types":["bug","grass"],"genus":"도롱이벌레포켓몬","flavorText":"진화한 장소에 따라 모습이\n바뀐다. 가까이 있는 재료가\n몸의 일부가 된다.","formDescription":"","stats":{"hp":{"value":60,"effort":0},"attack":{"value":59,"effort":0},"defense":{"value":85,"effort":0},"special-attack":{"value":79,"effort":0},"special-defense":{"value":105,"effort":2},"speed":{"value":36,"effort":0}}},{"id":414,"imgName":"mothim","name":"나메일","shape":"","color":{"l":0.97,"c":0.21,"h":110},"types":["bug","flying"],"genus":"나방포켓몬","flavorText":"꽃의 꿀을 매우 좋아한다.\n세꿀버리가 모아둔 꿀을\n가로채어 먹어 버린다.","formDescription":"","stats":{"hp":{"value":70,"effort":0},"attack":{"value":94,"effort":1},"defense":{"value":50,"effort":0},"special-attack":{"value":94,"effort":1},"special-defense":{"value":50,"effort":0},"speed":{"value":66,"effort":0}}},{"id":415,"imgName":"combee","name":"세꿀버리","shape":"","color":{"l":0.97,"c":0.21,"h":110},"types":["bug","flying"],"genus":"꼬마벌포켓몬","flavorText":"태어났을 때부터 3마리가 함께한다.\n비퀸을 기쁘게 하기 위해\n항상 꽃의 꿀을 모으고 있다.","formDescription":"","stats":{"hp":{"value":30,"effort":0},"attack":{"value":30,"effort":0},"defense":{"value":42,"effort":0},"special-attack":{"value":30,"effort":0},"special-defense":{"value":42,"effort":0},"speed":{"value":70,"effort":1}}},{"id":416,"imgName":"vespiquen","name":"비퀸","shape":"","color":{"l":0.97,"c":0.21,"h":110},"types":["bug","flying"],"genus":"벌집포켓몬","flavorText":"몸통은 아기들의 둥지다.\n여러 페로몬을 내어\n새끼들을 자유롭게 조종한다.","formDescription":"","stats":{"hp":{"value":70,"effort":0},"attack":{"value":80,"effort":0},"defense":{"value":102,"effort":1},"special-attack":{"value":80,"effort":0},"special-defense":{"value":102,"effort":1},"speed":{"value":40,"effort":0}}},{"id":417,"imgName":"pachirisu","name":"파치리스","shape":"","color":{"l":1,"c":0,"h":0},"types":["electric"],"genus":"전기다람쥐포켓몬","flavorText":"정전기가 모여 톡톡 튀는 솜털을\n자신이 좋아하는 나무열매와 함께\n나무줄기의 구멍에 숨긴다.","formDescription":"","stats":{"hp":{"value":60,"effort":0},"attack":{"value":45,"effort":0},"defense":{"value":70,"effort":0},"special-attack":{"value":45,"effort":0},"special-defense":{"value":90,"effort":0},"speed":{"value":95,"effort":1}}},{"id":418,"imgName":"buizel","name":"브이젤","shape":"","color":{"l":0.48,"c":0.16,"h":26},"types":["water"],"genus":"바다족제비포켓몬","flavorText":"2개의 꼬리를 스크루처럼\n돌려서 헤엄친다. 잠수할 때는\n공기주머니가 오그라든다.","formDescription":"","stats":{"hp":{"value":55,"effort":0},"attack":{"value":65,"effort":0},"defense":{"value":35,"effort":0},"special-attack":{"value":60,"effort":0},"special-defense":{"value":30,"effort":0},"speed":{"value":85,"effort":1}}},{"id":419,"imgName":"floatzel","name":"플로젤","shape":"","color":{"l":0.48,"c":0.16,"h":26},"types":["water"],"genus":"바다족제비포켓몬","flavorText":"발달한 부낭으로 뜬다.\n물에 빠진 사람을 구조하는 것을\n돕는 포켓몬이다.","formDescription":"","stats":{"hp":{"value":85,"effort":0},"attack":{"value":105,"effort":0},"defense":{"value":55,"effort":0},"special-attack":{"value":85,"effort":0},"special-defense":{"value":50,"effort":0},"speed":{"value":115,"effort":2}}},{"id":420,"imgName":"cherubi","name":"체리버","shape":"","color":{"l":0.87,"c":0.07,"h":7},"types":["grass"],"genus":"버찌포켓몬","flavorText":"햇빛으로 빨갛게 물들었다.\n영양분이 흡수되어 작은 구슬이\n시들면 곧 진화한다는 뜻이다.","formDescription":"","stats":{"hp":{"value":45,"effort":0},"attack":{"value":35,"effort":0},"defense":{"value":45,"effort":0},"special-attack":{"value":62,"effort":1},"special-defense":{"value":53,"effort":0},"speed":{"value":35,"effort":0}}},{"id":421,"imgName":"cherrim","name":"체리꼬","shape":"","color":{"l":0.42,"c":0.19,"h":328},"types":["grass"],"genus":"벚꽃포켓몬","flavorText":"봉오리가 태양의 빛을\n쬐어 꽃잎이 피면\n활발하게 움직일 수 있게 된다.","formDescription":"","stats":{"hp":{"value":70,"effort":0},"attack":{"value":60,"effort":0},"defense":{"value":70,"effort":0},"special-attack":{"value":87,"effort":2},"special-defense":{"value":78,"effort":0},"speed":{"value":85,"effort":0}}},{"id":422,"imgName":"shellos","name":"깝질무","shape":"","color":{"l":0.42,"c":0.19,"h":328},"types":["water"],"genus":"갯민숭달팽이포켓몬","flavorText":"부드러운 몸을 강하게 누르면\n보랏빛이 나는 정체불명의 액체가\n배어 나오므로 주의가 필요하다.","formDescription":"","stats":{"hp":{"value":76,"effort":1},"attack":{"value":48,"effort":0},"defense":{"value":48,"effort":0},"special-attack":{"value":57,"effort":0},"special-defense":{"value":62,"effort":0},"speed":{"value":34,"effort":0}}},{"id":423,"imgName":"gastrodon","name":"트리토돈","shape":"","color":{"l":0.42,"c":0.19,"h":328},"types":["water","ground"],"genus":"갯민숭달팽이포켓몬","flavorText":"천적에게 습격당했을 때는\n보라색 액체를\n몸에서 내어 도망간다.","formDescription":"","stats":{"hp":{"value":111,"effort":2},"attack":{"value":83,"effort":0},"defense":{"value":68,"effort":0},"special-attack":{"value":92,"effort":0},"special-defense":{"value":82,"effort":0},"speed":{"value":39,"effort":0}}},{"id":424,"imgName":"ambipom","name":"겟핸보숭","shape":"","color":{"l":0.42,"c":0.19,"h":328},"types":["normal"],"genus":"긴꼬리포켓몬","flavorText":"많은 무리로 행동한다.\n꼬리를 맞잡아 원을 만든다.\n우정의 표시인 듯하다.","formDescription":"","stats":{"hp":{"value":75,"effort":0},"attack":{"value":100,"effort":0},"defense":{"value":66,"effort":0},"special-attack":{"value":60,"effort":0},"special-defense":{"value":66,"effort":0},"speed":{"value":115,"effort":2}}},{"id":425,"imgName":"drifloon","name":"흔들풍손","shape":"","color":{"l":0.42,"c":0.19,"h":328},"types":["ghost","flying"],"genus":"풍선포켓몬","flavorText":"사람이나 포켓몬의 영혼이\n한데 모여 태어난 포켓몬이다.\n습기 많은 계절을 매우 좋아한다.","formDescription":"","stats":{"hp":{"value":90,"effort":1},"attack":{"value":50,"effort":0},"defense":{"value":34,"effort":0},"special-attack":{"value":60,"effort":0},"special-defense":{"value":44,"effort":0},"speed":{"value":70,"effort":0}}},{"id":426,"imgName":"drifblim","name":"둥실라이드","shape":"","color":{"l":0.42,"c":0.19,"h":328},"types":["ghost","flying"],"genus":"기구포켓몬","flavorText":"사람이나 포켓몬을 태우고 날지만\n바람에 떠밀려 다닐 뿐이므로\n어디로 날아갈지 모른다.","formDescription":"","stats":{"hp":{"value":150,"effort":2},"attack":{"value":80,"effort":0},"defense":{"value":44,"effort":0},"special-attack":{"value":90,"effort":0},"special-defense":{"value":54,"effort":0},"speed":{"value":80,"effort":0}}},{"id":427,"imgName":"buneary","name":"이어롤","shape":"","color":{"l":0.48,"c":0.16,"h":26},"types":["normal"],"genus":"토끼포켓몬","flavorText":"항상 말고 있는 귀를\n힘껏 늘리면 커다란\n바위도 간단히 부순다.","formDescription":"","stats":{"hp":{"value":55,"effort":0},"attack":{"value":66,"effort":0},"defense":{"value":44,"effort":0},"special-attack":{"value":44,"effort":0},"special-defense":{"value":56,"effort":0},"speed":{"value":85,"effort":1}}},{"id":428,"imgName":"lopunny","name":"이어롭","shape":"","color":{"l":0.48,"c":0.16,"h":26},"types":["normal"],"genus":"토끼포켓몬","flavorText":"경계심이 아주 강하다.\n위험을 감지하면 가뿐하게\n뛰어올라 달아난다.","formDescription":"","stats":{"hp":{"value":65,"effort":0},"attack":{"value":76,"effort":0},"defense":{"value":84,"effort":0},"special-attack":{"value":54,"effort":0},"special-defense":{"value":96,"effort":0},"speed":{"value":105,"effort":2}}},{"id":429,"imgName":"mismagius","name":"무우마직","shape":"","color":{"l":0.42,"c":0.19,"h":328},"types":["ghost"],"genus":"매지컬포켓몬","flavorText":"주문을 외는 포켓몬이다.\n상대를 고통스럽게 하는 것뿐만\n아니라 행복하게 하는 주문도 있다.","formDescription":"","stats":{"hp":{"value":60,"effort":0},"attack":{"value":60,"effort":0},"defense":{"value":60,"effort":0},"special-attack":{"value":105,"effort":1},"special-defense":{"value":105,"effort":1},"speed":{"value":105,"effort":0}}},{"id":430,"imgName":"honchkrow","name":"돈크로우","shape":"","color":{"l":0,"c":0,"h":0},"types":["dark","flying"],"genus":"큰형님포켓몬","flavorText":"돈크로우가 낮은 목소리로 울면\n즉시 니로우가 모여들기에\n밤을 부르는 자라고도 전해진다.","formDescription":"","stats":{"hp":{"value":100,"effort":0},"attack":{"value":125,"effort":2},"defense":{"value":52,"effort":0},"special-attack":{"value":105,"effort":0},"special-defense":{"value":52,"effort":0},"speed":{"value":71,"effort":0}}},{"id":431,"imgName":"glameow","name":"나옹마","shape":"","color":{"l":0.6,"c":0,"h":0},"types":["normal"],"genus":"내숭포켓몬","flavorText":"마음에 안 들면 발톱을 세우지만\n가끔 울음소리로 응석을 부리는\n성격이 일부에게 매우 인기가 있다.","formDescription":"","stats":{"hp":{"value":49,"effort":0},"attack":{"value":55,"effort":0},"defense":{"value":42,"effort":0},"special-attack":{"value":42,"effort":0},"special-defense":{"value":37,"effort":0},"speed":{"value":85,"effort":1}}},{"id":432,"imgName":"purugly","name":"몬냥이","shape":"","color":{"l":0.6,"c":0,"h":0},"types":["normal"],"genus":"얼룩고양이포켓몬","flavorText":"다른 포켓몬의 거처라 할지라도\n편안하면 눌러앉아\n자신의 거처로 삼아버린다.","formDescription":"","stats":{"hp":{"value":71,"effort":0},"attack":{"value":82,"effort":0},"defense":{"value":64,"effort":0},"special-attack":{"value":64,"effort":0},"special-defense":{"value":59,"effort":0},"speed":{"value":112,"effort":2}}},{"id":433,"imgName":"chingling","name":"랑딸랑","shape":"","color":{"l":0.97,"c":0.21,"h":110},"types":["psychic"],"genus":"방울포켓몬","flavorText":"뛸 때마다 딸랑딸랑 소리를 낸다.\n높은 주파수의 울음소리로\n상대의 귀를 들리지 않게 한다.","formDescription":"","stats":{"hp":{"value":45,"effort":0},"attack":{"value":30,"effort":0},"defense":{"value":50,"effort":0},"special-attack":{"value":65,"effort":1},"special-defense":{"value":50,"effort":0},"speed":{"value":45,"effort":0}}},{"id":434,"imgName":"stunky","name":"스컹뿡","shape":"","color":{"l":0.42,"c":0.19,"h":328},"types":["poison","dark"],"genus":"스컹크포켓몬","flavorText":"엉덩이에서 뿜어지는 역한 분비액의\n냄새는 범위 2km까지 멀리 퍼져\n주변의 포켓몬이 자리를 뜨게 한다.","formDescription":"","stats":{"hp":{"value":63,"effort":0},"attack":{"value":63,"effort":0},"defense":{"value":47,"effort":0},"special-attack":{"value":41,"effort":0},"special-defense":{"value":41,"effort":0},"speed":{"value":74,"effort":1}}},{"id":435,"imgName":"skuntank","name":"스컹탱크","shape":"","color":{"l":0.42,"c":0.19,"h":328},"types":["poison","dark"],"genus":"스컹크포켓몬","flavorText":"꼬리 끝에서 심한 냄새가 나는\n액체를 뿌려 공격한다.\n사정거리는 50m 이상이다.","formDescription":"","stats":{"hp":{"value":103,"effort":2},"attack":{"value":93,"effort":0},"defense":{"value":67,"effort":0},"special-attack":{"value":71,"effort":0},"special-defense":{"value":61,"effort":0},"speed":{"value":84,"effort":0}}},{"id":436,"imgName":"bronzor","name":"동미러","shape":"","color":{"l":0.52,"c":0.18,"h":142},"types":["steel","psychic"],"genus":"청동포켓몬","flavorText":"동미러의 등 모양에는\n신비한 힘이 깃들어 있다고\n옛날 사람들은 믿고 있었다.","formDescription":"","stats":{"hp":{"value":57,"effort":0},"attack":{"value":24,"effort":0},"defense":{"value":86,"effort":1},"special-attack":{"value":24,"effort":0},"special-defense":{"value":86,"effort":0},"speed":{"value":23,"effort":0}}},{"id":437,"imgName":"bronzong","name":"동탁군","shape":"","color":{"l":0.52,"c":0.18,"h":142},"types":["steel","psychic"],"genus":"동탁포켓몬","flavorText":"비구름을 부르는 포켓몬으로\n아주 옛날부터 떠받들어졌다.\n가끔 땅에 묻혀 있다.","formDescription":"","stats":{"hp":{"value":67,"effort":0},"attack":{"value":89,"effort":0},"defense":{"value":116,"effort":1},"special-attack":{"value":79,"effort":0},"special-defense":{"value":116,"effort":1},"speed":{"value":33,"effort":0}}},{"id":438,"imgName":"bonsly","name":"꼬지지","shape":"","color":{"l":0.48,"c":0.16,"h":26},"types":["rock"],"genus":"분재포켓몬","flavorText":"건조한 장소를 좋아한다.\n눈에서 물을 내어 몸의\n수분을 조절한다.","formDescription":"","stats":{"hp":{"value":50,"effort":0},"attack":{"value":80,"effort":0},"defense":{"value":95,"effort":1},"special-attack":{"value":10,"effort":0},"special-defense":{"value":45,"effort":0},"speed":{"value":10,"effort":0}}},{"id":439,"imgName":"mime-jr","name":"흉내내","shape":"","color":{"l":0.87,"c":0.07,"h":7},"types":["psychic","fairy"],"genus":"따라하기포켓몬","flavorText":"상대의 움직임을 똑같이\n흉내 내어 당황한\n사이에 재빨리 도망친다.","formDescription":"","stats":{"hp":{"value":20,"effort":0},"attack":{"value":25,"effort":0},"defense":{"value":45,"effort":0},"special-attack":{"value":70,"effort":0},"special-defense":{"value":90,"effort":1},"speed":{"value":60,"effort":0}}},{"id":440,"imgName":"happiny","name":"핑복","shape":"","color":{"l":0.87,"c":0.07,"h":7},"types":["normal"],"genus":"소꿉놀이포켓몬","flavorText":"알을 닮은 둥근 돌을\n배의 주머니에 넣고 있다.\n좋아하는 상대에게 돌을 준다.","formDescription":"","stats":{"hp":{"value":100,"effort":1},"attack":{"value":5,"effort":0},"defense":{"value":5,"effort":0},"special-attack":{"value":15,"effort":0},"special-defense":{"value":65,"effort":0},"speed":{"value":30,"effort":0}}},{"id":441,"imgName":"chatot","name":"페라페","shape":"","color":{"l":0,"c":0,"h":0},"types":["normal","flying"],"genus":"음표포켓몬","flavorText":"상대와 같은 울음소리를 내서\n동료라고 굳게 믿게 하여\n습격당하지 않도록 하고 있다.","formDescription":"","stats":{"hp":{"value":76,"effort":0},"attack":{"value":65,"effort":1},"defense":{"value":45,"effort":0},"special-attack":{"value":92,"effort":0},"special-defense":{"value":42,"effort":0},"speed":{"value":91,"effort":0}}},{"id":442,"imgName":"spiritomb","name":"화강돌","shape":"","color":{"l":0.42,"c":0.19,"h":328},"types":["ghost","dark"],"genus":"봉인포켓몬","flavorText":"108개의 영혼이 모여서\n태어난 포켓몬이다. 쐐기돌의\n균열과 연결되어 있다.","formDescription":"","stats":{"hp":{"value":50,"effort":0},"attack":{"value":92,"effort":0},"defense":{"value":108,"effort":1},"special-attack":{"value":92,"effort":0},"special-defense":{"value":108,"effort":1},"speed":{"value":35,"effort":0}}},{"id":443,"imgName":"gible","name":"딥상어동","shape":"","color":{"l":0.45,"c":0.31,"h":264},"types":["dragon","ground"],"genus":"육지상어포켓몬","flavorText":"지열로 데워진 구멍에서\n지낸다. 적이 가까이 오면 구멍에서\n뛰쳐나와 커다란 입으로 물어버린다.","formDescription":"","stats":{"hp":{"value":58,"effort":0},"attack":{"value":70,"effort":1},"defense":{"value":45,"effort":0},"special-attack":{"value":40,"effort":0},"special-defense":{"value":45,"effort":0},"speed":{"value":42,"effort":0}}},{"id":444,"imgName":"gabite","name":"한바이트","shape":"","color":{"l":0.45,"c":0.31,"h":264},"types":["dragon","ground"],"genus":"동굴포켓몬","flavorText":"반짝반짝 빛나는 것을\n아주 좋아하기에 동굴 안에서 발견한\n보물을 자신의 둥지에 모아둔다.","formDescription":"","stats":{"hp":{"value":68,"effort":0},"attack":{"value":90,"effort":2},"defense":{"value":65,"effort":0},"special-attack":{"value":50,"effort":0},"special-defense":{"value":55,"effort":0},"speed":{"value":82,"effort":0}}},{"id":445,"imgName":"garchomp","name":"한카리아스","shape":"","color":{"l":0.45,"c":0.31,"h":264},"types":["dragon","ground"],"genus":"마하포켓몬","flavorText":"몸을 접고 날개를\n펼치면 마치 제트기 같다.\n음속으로 날 수 있다.","formDescription":"","stats":{"hp":{"value":108,"effort":0},"attack":{"value":130,"effort":3},"defense":{"value":95,"effort":0},"special-attack":{"value":80,"effort":0},"special-defense":{"value":85,"effort":0},"speed":{"value":102,"effort":0}}},{"id":446,"imgName":"munchlax","name":"먹고자","shape":"","color":{"l":0,"c":0,"h":0},"types":["normal"],"genus":"대식가포켓몬","flavorText":"몸의 긴 털 안쪽에\n먹이를 숨기는 습성이 있다.\n숨긴 것을 잊어버린다.","formDescription":"","stats":{"hp":{"value":135,"effort":1},"attack":{"value":85,"effort":0},"defense":{"value":40,"effort":0},"special-attack":{"value":40,"effort":0},"special-defense":{"value":85,"effort":0},"speed":{"value":5,"effort":0}}},{"id":447,"imgName":"riolu","name":"리오르","shape":"","color":{"l":0.45,"c":0.31,"h":264},"types":["fighting"],"genus":"파문포켓몬","flavorText":"감정에 따라 모양이 변하는\n파동을 서로 내어 동료끼리\n커뮤니케이션을 취하고 있다.","formDescription":"","stats":{"hp":{"value":40,"effort":0},"attack":{"value":70,"effort":1},"defense":{"value":40,"effort":0},"special-attack":{"value":35,"effort":0},"special-defense":{"value":40,"effort":0},"speed":{"value":60,"effort":0}}},{"id":448,"imgName":"lucario","name":"루카리오","shape":"","color":{"l":0.45,"c":0.31,"h":264},"types":["fighting","steel"],"genus":"파동포켓몬","flavorText":"상대가 발하는 파동을\n감지하여 생각이나\n움직임을 간파할 수 있다.","formDescription":"","stats":{"hp":{"value":70,"effort":0},"attack":{"value":110,"effort":1},"defense":{"value":70,"effort":0},"special-attack":{"value":115,"effort":1},"special-defense":{"value":70,"effort":0},"speed":{"value":90,"effort":0}}},{"id":449,"imgName":"hippopotas","name":"히포포타스","shape":"","color":{"l":0.48,"c":0.16,"h":26},"types":["ground"],"genus":"하마포켓몬","flavorText":"건조한 땅에서 산다.\n땀 대신 모래알을\n몸에서 분비하는 포켓몬이다.","formDescription":"","stats":{"hp":{"value":68,"effort":0},"attack":{"value":72,"effort":0},"defense":{"value":78,"effort":1},"special-attack":{"value":38,"effort":0},"special-defense":{"value":42,"effort":0},"speed":{"value":32,"effort":0}}},{"id":450,"imgName":"hippowdon","name":"하마돈","shape":"","color":{"l":0.48,"c":0.16,"h":26},"types":["ground"],"genus":"중량포켓몬","flavorText":"크게 입을 벌려 자신의\n강함을 어필한다. 대량의\n모래를 일으켜 공격한다.","formDescription":"","stats":{"hp":{"value":108,"effort":0},"attack":{"value":112,"effort":0},"defense":{"value":118,"effort":2},"special-attack":{"value":68,"effort":0},"special-defense":{"value":72,"effort":0},"speed":{"value":47,"effort":0}}},{"id":451,"imgName":"skorupi","name":"스콜피","shape":"","color":{"l":0.42,"c":0.19,"h":328},"types":["poison","bug"],"genus":"전갈포켓몬","flavorText":"꼬리의 발톱으로 먹이를 집어\n독을 주입한다. 독이 퍼질 때까지\n절대 놓치지 않는 집념이 있다.","formDescription":"","stats":{"hp":{"value":40,"effort":0},"attack":{"value":50,"effort":0},"defense":{"value":90,"effort":1},"special-attack":{"value":30,"effort":0},"special-defense":{"value":55,"effort":0},"speed":{"value":65,"effort":0}}},{"id":452,"imgName":"drapion","name":"드래피온","shape":"","color":{"l":0.42,"c":0.19,"h":328},"types":["poison","dark"],"genus":"요괴전갈포켓몬","flavorText":"자랑거리인 파워로 상대를\n조각조각 낼 수 있으며 게다가\n맹독으로 마무리한다.","formDescription":"","stats":{"hp":{"value":70,"effort":0},"attack":{"value":90,"effort":0},"defense":{"value":110,"effort":2},"special-attack":{"value":60,"effort":0},"special-defense":{"value":75,"effort":0},"speed":{"value":95,"effort":0}}},{"id":453,"imgName":"croagunk","name":"삐딱구리","shape":"","color":{"l":0.45,"c":0.31,"h":264},"types":["poison","fighting"],"genus":"독설포켓몬","flavorText":"볼에 독주머니를 가지고 있다.\n상대의 틈을 노려 맹독이\n배인 손가락을 꿰찌른다.","formDescription":"","stats":{"hp":{"value":48,"effort":0},"attack":{"value":61,"effort":1},"defense":{"value":40,"effort":0},"special-attack":{"value":61,"effort":0},"special-defense":{"value":40,"effort":0},"speed":{"value":50,"effort":0}}},{"id":454,"imgName":"toxicroak","name":"독개굴","shape":"","color":{"l":0.45,"c":0.31,"h":264},"types":["poison","fighting"],"genus":"독설포켓몬","flavorText":"목 주변에 독주머니를 지녔다.\n목을 울리면 모여진 독이\n잘 섞여져서 강력해진다.","formDescription":"","stats":{"hp":{"value":83,"effort":0},"attack":{"value":106,"effort":2},"defense":{"value":65,"effort":0},"special-attack":{"value":86,"effort":0},"special-defense":{"value":65,"effort":0},"speed":{"value":85,"effort":0}}},{"id":455,"imgName":"carnivine","name":"무스틈니","shape":"","color":{"l":0.52,"c":0.18,"h":142},"types":["grass"],"genus":"벌레잡이포켓몬","flavorText":"달콤한 냄새의 타액으로 먹이를\n끌어들여 큰 턱으로 꿀꺽한다.\n하루에 걸쳐 먹이를 먹는다.","formDescription":"","stats":{"hp":{"value":74,"effort":0},"attack":{"value":100,"effort":2},"defense":{"value":72,"effort":0},"special-attack":{"value":90,"effort":0},"special-defense":{"value":72,"effort":0},"speed":{"value":46,"effort":0}}},{"id":456,"imgName":"finneon","name":"형광어","shape":"","color":{"l":0.45,"c":0.31,"h":264},"types":["water"],"genus":"비어포켓몬","flavorText":"몸의 옆쪽에 있는 줄에\n태양의 빛을 모아둘 수 있다.\n밤이 되면 아름답게 빛난다.","formDescription":"","stats":{"hp":{"value":49,"effort":0},"attack":{"value":49,"effort":0},"defense":{"value":56,"effort":0},"special-attack":{"value":49,"effort":0},"special-defense":{"value":61,"effort":0},"speed":{"value":66,"effort":1}}},{"id":457,"imgName":"lumineon","name":"네오라이트","shape":"","color":{"l":0.45,"c":0.31,"h":264},"types":["water"],"genus":"네온포켓몬","flavorText":"깊은 바다의 밑바닥에서 산다.\n4개의 지느러미 무늬를 반짝거려\n먹이를 끌어들인다.","formDescription":"","stats":{"hp":{"value":69,"effort":0},"attack":{"value":69,"effort":0},"defense":{"value":76,"effort":0},"special-attack":{"value":69,"effort":0},"special-defense":{"value":86,"effort":0},"speed":{"value":91,"effort":2}}},{"id":458,"imgName":"mantyke","name":"타만타","shape":"","color":{"l":0.45,"c":0.31,"h":264},"types":["water","flying"],"genus":"연포켓몬","flavorText":"등의 무늬는 지역에 따라\n달라진다. 총어 무리에\n섞여 헤엄치는 일이 많다.","formDescription":"","stats":{"hp":{"value":45,"effort":0},"attack":{"value":20,"effort":0},"defense":{"value":50,"effort":0},"special-attack":{"value":60,"effort":0},"special-defense":{"value":120,"effort":1},"speed":{"value":50,"effort":0}}},{"id":459,"imgName":"snover","name":"눈쓰개","shape":"","color":{"l":1,"c":0,"h":0},"types":["grass","ice"],"genus":"얼음나무포켓몬","flavorText":"추운 계절에는 산기슭까지\n내려오지만 봄이 되면 눈이\n남아 있는 산 정상으로 돌아간다.","formDescription":"","stats":{"hp":{"value":60,"effort":0},"attack":{"value":62,"effort":1},"defense":{"value":50,"effort":0},"special-attack":{"value":62,"effort":0},"special-defense":{"value":60,"effort":0},"speed":{"value":40,"effort":0}}},{"id":460,"imgName":"abomasnow","name":"눈설왕","shape":"","color":{"l":1,"c":0,"h":0},"types":["grass","ice"],"genus":"얼음나무포켓몬","flavorText":"블리자드를 발생시켜 주변\n일대를 새하얗게 만든다.\n별명은 아이스 몬스터다.","formDescription":"","stats":{"hp":{"value":90,"effort":0},"attack":{"value":92,"effort":1},"defense":{"value":75,"effort":0},"special-attack":{"value":92,"effort":1},"special-defense":{"value":85,"effort":0},"speed":{"value":60,"effort":0}}},{"id":461,"imgName":"weavile","name":"포푸니라","shape":"","color":{"l":0,"c":0,"h":0},"types":["dark","ice"],"genus":"갈고리손톱포켓몬","flavorText":"눈이 많은 지방에 서식한다.\n수목에 발톱으로 사인을 그려\n동료에게 신호를 보낸다.","formDescription":"","stats":{"hp":{"value":70,"effort":0},"attack":{"value":120,"effort":1},"defense":{"value":65,"effort":0},"special-attack":{"value":45,"effort":0},"special-defense":{"value":85,"effort":0},"speed":{"value":125,"effort":1}}},{"id":462,"imgName":"magnezone","name":"자포코일","shape":"","color":{"l":0.6,"c":0,"h":0},"types":["electric","steel"],"genus":"자기장포켓몬","flavorText":"너무 강한 자력을 내어\n자포코일끼리 끌어당겨\n전혀 못 움직이기도 한다.","formDescription":"","stats":{"hp":{"value":70,"effort":0},"attack":{"value":70,"effort":0},"defense":{"value":115,"effort":0},"special-attack":{"value":130,"effort":3},"special-defense":{"value":90,"effort":0},"speed":{"value":60,"effort":0}}},{"id":463,"imgName":"lickilicky","name":"내룸벨트","shape":"","color":{"l":0.87,"c":0.07,"h":7},"types":["normal"],"genus":"핥기포켓몬","flavorText":"타액에는 어떤 것도 녹이는\n성분이 충분히 포함되어 있어\n핥으면 언제까지나 마비된다.","formDescription":"","stats":{"hp":{"value":110,"effort":3},"attack":{"value":85,"effort":0},"defense":{"value":95,"effort":0},"special-attack":{"value":80,"effort":0},"special-defense":{"value":95,"effort":0},"speed":{"value":50,"effort":0}}},{"id":464,"imgName":"rhyperior","name":"거대코뿌리","shape":"","color":{"l":0.6,"c":0,"h":0},"types":["ground","rock"],"genus":"드릴포켓몬","flavorText":"손바닥의 구멍에서 꼬마돌을\n발사한다. 전신의 프로텍터는\n화산의 분화도 견뎌낸다.","formDescription":"","stats":{"hp":{"value":115,"effort":0},"attack":{"value":140,"effort":3},"defense":{"value":130,"effort":0},"special-attack":{"value":55,"effort":0},"special-defense":{"value":55,"effort":0},"speed":{"value":40,"effort":0}}},{"id":465,"imgName":"tangrowth","name":"덩쿠림보","shape":"","color":{"l":0.45,"c":0.31,"h":264},"types":["grass"],"genus":"넝쿨포켓몬","flavorText":"식물의 덩굴로 이루어진 팔을\n늘여서 먹이를 포박한다.\n팔을 먹혀도 아무렇지도 않다.","formDescription":"","stats":{"hp":{"value":100,"effort":0},"attack":{"value":100,"effort":0},"defense":{"value":125,"effort":2},"special-attack":{"value":110,"effort":0},"special-defense":{"value":50,"effort":0},"speed":{"value":50,"effort":0}}},{"id":466,"imgName":"electivire","name":"에레키블","shape":"","color":{"l":0.97,"c":0.21,"h":110},"types":["electric"],"genus":"뇌전포켓몬","flavorText":"전기를 가득 모으면\n2개의 뿔 사이에서 세차게\n푸르스름한 불티를 뿌린다.","formDescription":"","stats":{"hp":{"value":75,"effort":0},"attack":{"value":123,"effort":3},"defense":{"value":67,"effort":0},"special-attack":{"value":95,"effort":0},"special-defense":{"value":85,"effort":0},"speed":{"value":95,"effort":0}}},{"id":467,"imgName":"magmortar","name":"마그마번","shape":"","color":{"l":0.63,"c":0.26,"h":29},"types":["fire"],"genus":"폭염포켓몬","flavorText":"팔 끝에서 섭씨 2000도의\n불구슬을 발사한다.\n화산의 분화구를 거처로 삼는다.","formDescription":"","stats":{"hp":{"value":75,"effort":0},"attack":{"value":95,"effort":0},"defense":{"value":67,"effort":0},"special-attack":{"value":125,"effort":3},"special-defense":{"value":95,"effort":0},"speed":{"value":83,"effort":0}}},{"id":468,"imgName":"togekiss","name":"토게키스","shape":"","color":{"l":1,"c":0,"h":0},"types":["fairy","flying"],"genus":"축복포켓몬","flavorText":"다툼이 없는 평화로운 땅에\n토게키스가 나타나 여러 가지\n은총을 나눠줬다고 전해진다.","formDescription":"","stats":{"hp":{"value":85,"effort":0},"attack":{"value":50,"effort":0},"defense":{"value":95,"effort":0},"special-attack":{"value":120,"effort":2},"special-defense":{"value":115,"effort":1},"speed":{"value":80,"effort":0}}},{"id":469,"imgName":"yanmega","name":"메가자리","shape":"","color":{"l":0.52,"c":0.18,"h":142},"types":["bug","flying"],"genus":"깨비잠자리포켓몬","flavorText":"고속으로 날아서 스친\n상대의 목을 한순간에\n물어뜯는 싸움법을 선호한다.","formDescription":"","stats":{"hp":{"value":86,"effort":0},"attack":{"value":76,"effort":2},"defense":{"value":86,"effort":0},"special-attack":{"value":116,"effort":0},"special-defense":{"value":56,"effort":0},"speed":{"value":95,"effort":0}}},{"id":470,"imgName":"leafeon","name":"리피아","shape":"","color":{"l":0.52,"c":0.18,"h":142},"types":["grass"],"genus":"심록포켓몬","flavorText":"맑은 날에 잠든 리피아는\n광합성을 해서 깨끗한\n공기를 만들고 있다.","formDescription":"","stats":{"hp":{"value":65,"effort":0},"attack":{"value":110,"effort":0},"defense":{"value":130,"effort":2},"special-attack":{"value":60,"effort":0},"special-defense":{"value":65,"effort":0},"speed":{"value":95,"effort":0}}},{"id":471,"imgName":"glaceon","name":"글레이시아","shape":"","color":{"l":0.45,"c":0.31,"h":264},"types":["ice"],"genus":"신설포켓몬","flavorText":"체온을 컨트롤하는 것으로\n주위의 공기를 얼려서\n다이아몬드 더스트를 날린다.","formDescription":"","stats":{"hp":{"value":65,"effort":0},"attack":{"value":60,"effort":0},"defense":{"value":110,"effort":0},"special-attack":{"value":130,"effort":2},"special-defense":{"value":95,"effort":0},"speed":{"value":65,"effort":0}}},{"id":472,"imgName":"gliscor","name":"글라이온","shape":"","color":{"l":0.42,"c":0.19,"h":328},"types":["ground","flying"],"genus":"송곳니전갈포켓몬","flavorText":"꼬리로 나뭇가지에 매달려\n먹이를 관찰한다. 틈을\n봐서 상공에서 덮친다.","formDescription":"","stats":{"hp":{"value":75,"effort":0},"attack":{"value":95,"effort":0},"defense":{"value":125,"effort":2},"special-attack":{"value":45,"effort":0},"special-defense":{"value":75,"effort":0},"speed":{"value":95,"effort":0}}},{"id":473,"imgName":"mamoswine","name":"맘모꾸리","shape":"","color":{"l":0.48,"c":0.16,"h":26},"types":["ice","ground"],"genus":"2개송곳니포켓몬","flavorText":"1만 년 전의 얼음 밑에서\n발견된 적이 있을 정도로\n오랜 옛날부터 있었던 포켓몬이다.","formDescription":"","stats":{"hp":{"value":110,"effort":0},"attack":{"value":130,"effort":3},"defense":{"value":80,"effort":0},"special-attack":{"value":70,"effort":0},"special-defense":{"value":60,"effort":0},"speed":{"value":80,"effort":0}}},{"id":474,"imgName":"porygon-z","name":"폴리곤Z","shape":"","color":{"l":0.63,"c":0.26,"h":29},"types":["normal"],"genus":"가상포켓몬","flavorText":"더욱 우수한 포켓몬으로 만들고자\n프로그램을 추가했지만 어쩐지\n괴상하게 행동하기 시작했다.","formDescription":"","stats":{"hp":{"value":85,"effort":0},"attack":{"value":80,"effort":0},"defense":{"value":70,"effort":0},"special-attack":{"value":135,"effort":3},"special-defense":{"value":75,"effort":0},"speed":{"value":90,"effort":0}}},{"id":475,"imgName":"gallade","name":"엘레이드","shape":"","color":{"l":1,"c":0,"h":0},"types":["psychic","fighting"],"genus":"검포켓몬","flavorText":"상대의 생각을 민감하게\n포착하는 능력을 가졌기 때문에\n먼저 공격할 수 있다.","formDescription":"","stats":{"hp":{"value":68,"effort":0},"attack":{"value":125,"effort":3},"defense":{"value":65,"effort":0},"special-attack":{"value":65,"effort":0},"special-defense":{"value":115,"effort":0},"speed":{"value":80,"effort":0}}},{"id":476,"imgName":"probopass","name":"대코파스","shape":"","color":{"l":0.6,"c":0,"h":0},"types":["rock","steel"],"genus":"콤파스포켓몬","flavorText":"전신에서 강한 자력을 발산하고\n있다. 꼬마코파스라고 불리는\n3개의 유닛을 조종한다.","formDescription":"","stats":{"hp":{"value":60,"effort":0},"attack":{"value":55,"effort":0},"defense":{"value":145,"effort":1},"special-attack":{"value":75,"effort":0},"special-defense":{"value":150,"effort":2},"speed":{"value":40,"effort":0}}},{"id":477,"imgName":"dusknoir","name":"야느와르몽","shape":"","color":{"l":0,"c":0,"h":0},"types":["ghost"],"genus":"움켜쥠포켓몬","flavorText":"탄력 있는 몸 안에\n갈 곳 없는 영혼을 가두어\n저승으로 데려간다고 전해진다.","formDescription":"","stats":{"hp":{"value":45,"effort":0},"attack":{"value":100,"effort":0},"defense":{"value":135,"effort":1},"special-attack":{"value":65,"effort":0},"special-defense":{"value":135,"effort":2},"speed":{"value":45,"effort":0}}},{"id":478,"imgName":"froslass","name":"눈여아","shape":"","color":{"l":1,"c":0,"h":0},"types":["ice","ghost"],"genus":"설국포켓몬","flavorText":"마이너스 50도의 냉기를 뿜어\n상대를 얼려 버린다. 몸통 같은\n부분은 실제로는 빈 공간이다.","formDescription":"","stats":{"hp":{"value":70,"effort":0},"attack":{"value":80,"effort":0},"defense":{"value":70,"effort":0},"special-attack":{"value":80,"effort":0},"special-defense":{"value":70,"effort":0},"speed":{"value":110,"effort":2}}},{"id":479,"imgName":"rotom","name":"로토무","shape":"","color":{"l":0.63,"c":0.26,"h":29},"types":["electric","ghost"],"genus":"플라스마포켓몬","flavorText":"특수한 모터를 움직이는\n동력원으로서 긴 시간 동안\n연구되었던 포켓몬이다.","formDescription":"","stats":{"hp":{"value":50,"effort":0},"attack":{"value":50,"effort":0},"defense":{"value":77,"effort":0},"special-attack":{"value":95,"effort":1},"special-defense":{"value":77,"effort":0},"speed":{"value":91,"effort":1}}},{"id":480,"imgName":"uxie","name":"유크시","shape":"","color":{"l":0.97,"c":0.21,"h":110},"types":["psychic"],"genus":"지식포켓몬","flavorText":"지식의 신이라 불리고 있다.\n눈을 마주친 사람의 기억을 지워\n버리는 힘을 가지고 있다고 한다.","formDescription":"","stats":{"hp":{"value":75,"effort":0},"attack":{"value":75,"effort":0},"defense":{"value":130,"effort":2},"special-attack":{"value":75,"effort":0},"special-defense":{"value":130,"effort":1},"speed":{"value":95,"effort":0}}},{"id":481,"imgName":"mesprit","name":"엠라이트","shape":"","color":{"l":0.87,"c":0.07,"h":7},"types":["psychic"],"genus":"감정포켓몬","flavorText":"슬픔의 괴로움과 즐거움의 소중함을\n사람들에게 가르쳐 주었다.\n감정의 신이라 불리고 있다.","formDescription":"","stats":{"hp":{"value":80,"effort":0},"attack":{"value":105,"effort":1},"defense":{"value":105,"effort":0},"special-attack":{"value":105,"effort":1},"special-defense":{"value":105,"effort":1},"speed":{"value":80,"effort":0}}},{"id":482,"imgName":"azelf","name":"아그놈","shape":"","color":{"l":0.45,"c":0.31,"h":264},"types":["psychic"],"genus":"의지포켓몬","flavorText":"의지의 신이라 불리고 있다.\n호수의 밑바닥에서 계속 잠을 자며\n세계의 균형을 지키고 있다.","formDescription":"","stats":{"hp":{"value":75,"effort":0},"attack":{"value":125,"effort":2},"defense":{"value":70,"effort":0},"special-attack":{"value":125,"effort":1},"special-defense":{"value":70,"effort":0},"speed":{"value":115,"effort":0}}},{"id":483,"imgName":"dialga","name":"디아루가","shape":"","color":{"l":1,"c":0,"h":0},"types":["steel","dragon"],"genus":"시간포켓몬","flavorText":"디아루가가 태어남으로써\n시간이 움직이기 시작했다는\n전설이 내려오는 포켓몬이다.","formDescription":"","stats":{"hp":{"value":100,"effort":0},"attack":{"value":120,"effort":0},"defense":{"value":120,"effort":0},"special-attack":{"value":150,"effort":3},"special-defense":{"value":100,"effort":0},"speed":{"value":90,"effort":0}}},{"id":484,"imgName":"palkia","name":"펄기아","shape":"","color":{"l":0.42,"c":0.19,"h":328},"types":["water","dragon"],"genus":"공간포켓몬","flavorText":"평행으로 늘어선 공간의\n틈새에 산다고 전해진다.\n신화에 등장하는 포켓몬이다.","formDescription":"","stats":{"hp":{"value":90,"effort":0},"attack":{"value":120,"effort":0},"defense":{"value":100,"effort":0},"special-attack":{"value":150,"effort":3},"special-defense":{"value":120,"effort":0},"speed":{"value":100,"effort":0}}},{"id":485,"imgName":"heatran","name":"히드런","shape":"","color":{"l":0.48,"c":0.16,"h":26},"types":["fire","steel"],"genus":"화구포켓몬","flavorText":"화산의 동굴에서 서식한다.\n십자형의 발톱을 박아서\n벽이나 천장을 돌아다닌다.","formDescription":"","stats":{"hp":{"value":91,"effort":0},"attack":{"value":90,"effort":0},"defense":{"value":106,"effort":0},"special-attack":{"value":130,"effort":3},"special-defense":{"value":106,"effort":0},"speed":{"value":77,"effort":0}}},{"id":486,"imgName":"regigigas","name":"레지기가스","shape":"","color":{"l":1,"c":0,"h":0},"types":["normal"],"genus":"거대포켓몬","flavorText":"특수한 빙산이나 암석,\n마그마에서 자신의 모습과 닮은\n포켓몬을 만들었다고 전해진다.","formDescription":"","stats":{"hp":{"value":110,"effort":0},"attack":{"value":160,"effort":3},"defense":{"value":110,"effort":0},"special-attack":{"value":80,"effort":0},"special-defense":{"value":110,"effort":0},"speed":{"value":100,"effort":0}}},{"id":487,"imgName":"giratina-altered","name":"기라티나","shape":"","color":{"l":0,"c":0,"h":0},"types":["ghost","dragon"],"genus":"반골포켓몬","flavorText":"상식이 통하지 않는\n이 세상의 이면에 있다고 불리는\n깨어진 세계에 서식한다.","formDescription":"","stats":{"hp":{"value":150,"effort":3},"attack":{"value":100,"effort":0},"defense":{"value":120,"effort":0},"special-attack":{"value":100,"effort":0},"special-defense":{"value":120,"effort":0},"speed":{"value":90,"effort":0}}},{"id":488,"imgName":"cresselia","name":"크레세리아","shape":"","color":{"l":0.97,"c":0.21,"h":110},"types":["psychic"],"genus":"초승달포켓몬","flavorText":"비행할 때는 베일 같은\n날개에서 빛나는 입자를 낸다.\n초승달의 화신으로 불리고 있다.","formDescription":"","stats":{"hp":{"value":120,"effort":0},"attack":{"value":70,"effort":0},"defense":{"value":110,"effort":0},"special-attack":{"value":75,"effort":0},"special-defense":{"value":120,"effort":3},"speed":{"value":85,"effort":0}}},{"id":489,"imgName":"phione","name":"피오네","shape":"","color":{"l":0.45,"c":0.31,"h":264},"types":["water"],"genus":"해양포켓몬","flavorText":"바다 온도가 높아지면\n머리의 부낭을 부풀려서\n해수면을 집단으로 떠돈다.","formDescription":"","stats":{"hp":{"value":80,"effort":1},"attack":{"value":80,"effort":0},"defense":{"value":80,"effort":0},"special-attack":{"value":80,"effort":0},"special-defense":{"value":80,"effort":0},"speed":{"value":80,"effort":0}}},{"id":490,"imgName":"manaphy","name":"마나피","shape":"","color":{"l":0.45,"c":0.31,"h":264},"types":["water"],"genus":"회유포켓몬","flavorText":"태어났을 때부터 가지고 있는\n이상한 힘을 쓰면 어떤 포켓몬과도\n마음이 서로 통하게 된다.","formDescription":"","stats":{"hp":{"value":100,"effort":3},"attack":{"value":100,"effort":0},"defense":{"value":100,"effort":0},"special-attack":{"value":100,"effort":0},"special-defense":{"value":100,"effort":0},"speed":{"value":100,"effort":0}}},{"id":491,"imgName":"darkrai","name":"다크라이","shape":"","color":{"l":0,"c":0,"h":0},"types":["dark"],"genus":"암흑포켓몬","flavorText":"깊은 잠으로 끌어들이는 힘으로\n사람과 포켓몬에게 악몽을 꾸게 해\n자신의 영역에서 쫓아낸다.","formDescription":"","stats":{"hp":{"value":70,"effort":0},"attack":{"value":90,"effort":0},"defense":{"value":90,"effort":0},"special-attack":{"value":135,"effort":2},"special-defense":{"value":90,"effort":0},"speed":{"value":125,"effort":1}}},{"id":492,"imgName":"shaymin-land","name":"쉐이미","shape":"","color":{"l":0.52,"c":0.18,"h":142},"types":["grass"],"genus":"감사포켓몬","flavorText":"대기의 독소를 분해해서\n거칠어진 대지를 일순간에\n꽃밭으로 만드는 힘을 가지고 있다.","formDescription":"","stats":{"hp":{"value":100,"effort":3},"attack":{"value":100,"effort":0},"defense":{"value":100,"effort":0},"special-attack":{"value":100,"effort":0},"special-defense":{"value":100,"effort":0},"speed":{"value":100,"effort":0}}},{"id":493,"imgName":"arceus","name":"아르세우스","shape":"","color":{"l":1,"c":0,"h":0},"types":["normal"],"genus":"창조포켓몬","flavorText":"알에서 모습을 나타내\n모든 세계를 창조했다고\n신오신화에서 묘사된다.","formDescription":"","stats":{"hp":{"value":120,"effort":3},"attack":{"value":120,"effort":0},"defense":{"value":120,"effort":0},"special-attack":{"value":120,"effort":0},"special-defense":{"value":120,"effort":0},"speed":{"value":120,"effort":0}}}]